{"type":"FeatureCollection","metadata":{"generated":1597556159000,"url":"https://earthquake.usgs.gov/fdsnws/event/1/query?format=geojson&starttime=1957-10-01&endtime=1957-10-31","title":"USGS Earthquakes","status":200,"api":"1.10.3","count":61},"features":[{"type":"Feature","properties":{"mag":3.11,"place":"2km SE of Rowland Heights, CA","time":-384061140550,"updated":1454005454750,"tz":null,"url":"https://earthquake.usgs.gov/earthquakes/eventpage/ci3296241","detail":"https://earthquake.usgs.gov/fdsnws/event/1/query?eventid=ci3296241&format=geojson","felt":null,"cdi":null,"mmi":null,"alert":null,"status":"reviewed","tsunami":0,"sig":149,"net":"ci","code":"3296241","ids":",ci3296241,","sources":",ci,","types":",origin,phase-data,","nst":7,"dmin":0.2951,"rms":0.29,"gap":110,"magType":"ml","type":"earthquake","title":"M 3.1 - 2km SE of Rowland Heights, CA"},"geometry":{"type":"Point","coordinates":[-117.8918333,33.9655,1.79]},"id":"ci3296241"},
{"type":"Feature","properties":{"mag":2.73,"place":"22km S of Bodfish, CA","time":-384086804350,"updated":1454004912750,"tz":null,"url":"https://earthquake.usgs.gov/earthquakes/eventpage/ci3296240","detail":"https://earthquake.usgs.gov/fdsnws/event/1/query?eventid=ci3296240&format=geojson","felt":null,"cdi":null,"mmi":null,"alert":null,"status":"reviewed","tsunami":0,"sig":115,"net":"ci","code":"3296240","ids":",ci3296240,","sources":",ci,","types":",origin,phase-data,","nst":5,"dmin":0.2731,"rms":0.19,"gap":161,"magType":"ml","type":"earthquake","title":"M 2.7 - 22km S of Bodfish, CA"},"geometry":{"type":"Point","coordinates":[-118.5133333,35.391,2.43]},"id":"ci3296240"},
{"type":"Feature","properties":{"mag":2.63,"place":"7km SSW of Devore, CA","time":-384095978650,"updated":1454004356470,"tz":null,"url":"https://earthquake.usgs.gov/earthquakes/eventpage/ci3296239","detail":"https://earthquake.usgs.gov/fdsnws/event/1/query?eventid=ci3296239&format=geojson","felt":null,"cdi":null,"mmi":null,"alert":null,"status":"reviewed","tsunami":0,"sig":106,"net":"ci","code":"3296239","ids":",ci3296239,","sources":",ci,","types":",origin,phase-data,","nst":6,"dmin":0.1733,"rms":0.74,"gap":185,"magType":"ml","type":"earthquake","title":"M 2.6 - 7km SSW of Devore, CA"},"geometry":{"type":"Point","coordinates":[-117.422,34.1628333,15.61]},"id":"ci3296239"},
{"type":"Feature","properties":{"mag":5.8,"place":"Dodecanese Islands, Greece","time":-384107379000,"updated":1431543172000,"tz":null,"url":"https://earthquake.usgs.gov/earthquakes/eventpage/iscgem887449","detail":"https://earthquake.usgs.gov/fdsnws/event/1/query?eventid=iscgem887449&format=geojson","felt":null,"cdi":null,"mmi":null,"alert":null,"status":"automatic","tsunami":0,"sig":518,"net":"iscgem","code":"887449","ids":",iscgem887449,","sources":",iscgem,","types":",origin,","nst":null,"dmin":null,"rms":null,"gap":null,"magType":"mw","type":"earthquake","title":"M 5.8 - Dodecanese Islands, Greece"},"geometry":{"type":"Point","coordinates":[27.718,35.238,15]},"id":"iscgem887449"},
{"type":"Feature","properties":{"mag":null,"place":"Fox Islands, Aleutian Islands, Alaska","time":-384126412000,"updated":1528145024000,"tz":null,"url":"https://earthquake.usgs.gov/earthquakes/eventpage/ushis2265","detail":"https://earthquake.usgs.gov/fdsnws/event/1/query?eventid=ushis2265&format=geojson","felt":null,"cdi":null,"mmi":null,"alert":null,"status":"reviewed","tsunami":0,"sig":0,"net":"ushis","code":"2265","ids":",ushis2265,","sources":",ushis,","types":",impact-text,origin,","nst":null,"dmin":null,"rms":null,"gap":null,"magType":null,"type":"earthquake","title":"M ? - Fox Islands, Aleutian Islands, Alaska"},"geometry":{"type":"Point","coordinates":[-166.82,53.12,null]},"id":"ushis2265"},
{"type":"Feature","properties":{"mag":5.7,"place":"Dodecanese Islands, Greece","time":-384128217000,"updated":1431543172000,"tz":null,"url":"https://earthquake.usgs.gov/earthquakes/eventpage/iscgem887445","detail":"https://earthquake.usgs.gov/fdsnws/event/1/query?eventid=iscgem887445&format=geojson","felt":null,"cdi":null,"mmi":null,"alert":null,"status":"automatic","tsunami":0,"sig":500,"net":"iscgem","code":"887445","ids":",iscgem887445,","sources":",iscgem,","types":",origin,","nst":null,"dmin":null,"rms":null,"gap":null,"magType":"mw","type":"earthquake","title":"M 5.7 - Dodecanese Islands, Greece"},"geometry":{"type":"Point","coordinates":[27.314,35.205,15]},"id":"iscgem887445"},
{"type":"Feature","properties":{"mag":3.23,"place":"20km WNW of Desert Center, CA","time":-384260123910,"updated":1459570072339,"tz":null,"url":"https://earthquake.usgs.gov/earthquakes/eventpage/ci3296238","detail":"https://earthquake.usgs.gov/fdsnws/event/1/query?eventid=ci3296238&format=geojson","felt":null,"cdi":null,"mmi":null,"alert":null,"status":"reviewed","tsunami":0,"sig":161,"net":"ci","code":"3296238","ids":",ci3296238,","sources":",ci,","types":",nearby-cities,origin,phase-data,","nst":4,"dmin":0.1143,"rms":0.38,"gap":289,"magType":"ml","type":"earthquake","title":"M 3.2 - 20km WNW of Desert Center, CA"},"geometry":{"type":"Point","coordinates":[-115.578,33.81,10.84]},"id":"ci3296238"},
{"type":"Feature","properties":{"mag":2.89,"place":"9km WSW of Isla Vista, CA","time":-384265138090,"updated":1454004069930,"tz":null,"url":"https://earthquake.usgs.gov/earthquakes/eventpage/ci3296237","detail":"https://earthquake.usgs.gov/fdsnws/event/1/query?eventid=ci3296237&format=geojson","felt":null,"cdi":null,"mmi":null,"alert":null,"status":"reviewed","tsunami":0,"sig":128,"net":"ci","code":"3296237","ids":",ci3296237,","sources":",ci,","types":",origin,phase-data,","nst":7,"dmin":null,"rms":0.54,"gap":240,"magType":"ml","type":"earthquake","title":"M 2.9 - 9km WSW of Isla Vista, CA"},"geometry":{"type":"Point","coordinates":[-119.9425,34.3743333,6]},"id":"ci3296237"},
{"type":"Feature","properties":{"mag":7.6,"place":"near the east coast of the Kamchatka Peninsula, Russia","time":-384312438000,"updated":1594359887604,"tz":null,"url":"https://earthquake.usgs.gov/earthquakes/eventpage/iscgem887437","detail":"https://earthquake.usgs.gov/fdsnws/event/1/query?eventid=iscgem887437&format=geojson","felt":null,"cdi":null,"mmi":7.025,"alert":null,"status":"automatic","tsunami":0,"sig":889,"net":"iscgem","code":"887437","ids":",iscgem887437,","sources":",iscgem,","types":",origin,shakemap,","nst":null,"dmin":null,"rms":null,"gap":null,"magType":"mw","type":"earthquake","title":"M 7.6 - near the east coast of the Kamchatka Peninsula, Russia"},"geometry":{"type":"Point","coordinates":[161.134,55.75,147.8]},"id":"iscgem887437"},
{"type":"Feature","properties":{"mag":2.34,"place":"13km E of Santa Barbara Is., CA","time":-384337166640,"updated":1454005184660,"tz":null,"url":"https://earthquake.usgs.gov/earthquakes/eventpage/ci3296234","detail":"https://earthquake.usgs.gov/fdsnws/event/1/query?eventid=ci3296234&format=geojson","felt":null,"cdi":null,"mmi":null,"alert":null,"status":"reviewed","tsunami":0,"sig":84,"net":"ci","code":"3296234","ids":",ci3296234,","sources":",ci,","types":",origin,phase-data,","nst":7,"dmin":null,"rms":0.8,"gap":156,"magType":"mh","type":"earthquake","title":"M 2.3 - 13km E of Santa Barbara Is., CA"},"geometry":{"type":"Point","coordinates":[-118.9206667,33.4606667,6]},"id":"ci3296234"},
{"type":"Feature","properties":{"mag":3.18,"place":"3km SW of San Bernardino, CA","time":-384338078950,"updated":1454005184020,"tz":null,"url":"https://earthquake.usgs.gov/earthquakes/eventpage/ci3296233","detail":"https://earthquake.usgs.gov/fdsnws/event/1/query?eventid=ci3296233&format=geojson","felt":null,"cdi":null,"mmi":null,"alert":null,"status":"reviewed","tsunami":0,"sig":156,"net":"ci","code":"3296233","ids":",ci3296233,","sources":",ci,","types":",origin,phase-data,","nst":5,"dmin":0.1267,"rms":0.45,"gap":184,"magType":"ml","type":"earthquake","title":"M 3.2 - 3km SW of San Bernardino, CA"},"geometry":{"type":"Point","coordinates":[-117.311,34.1086667,15.15]},"id":"ci3296233"},
{"type":"Feature","properties":{"mag":6.1,"place":"Kalimantan, Indonesia","time":-384428578000,"updated":1594359870902,"tz":null,"url":"https://earthquake.usgs.gov/earthquakes/eventpage/iscgem887434","detail":"https://earthquake.usgs.gov/fdsnws/event/1/query?eventid=iscgem887434&format=geojson","felt":null,"cdi":null,"mmi":7.01,"alert":null,"status":"automatic","tsunami":0,"sig":572,"net":"iscgem","code":"887434","ids":",iscgem887434,","sources":",iscgem,","types":",origin,shakemap,","nst":null,"dmin":null,"rms":null,"gap":null,"magType":"mw","type":"earthquake","title":"M 6.1 - Kalimantan, Indonesia"},"geometry":{"type":"Point","coordinates":[116.012,-1.756,20]},"id":"iscgem887434"},
{"type":"Feature","properties":{"mag":3.74,"place":"27km ESE of Maneadero, B.C., MX","time":-384501803840,"updated":1454005183360,"tz":null,"url":"https://earthquake.usgs.gov/earthquakes/eventpage/ci3296232","detail":"https://earthquake.usgs.gov/fdsnws/event/1/query?eventid=ci3296232&format=geojson","felt":null,"cdi":null,"mmi":null,"alert":null,"status":"reviewed","tsunami":0,"sig":215,"net":"ci","code":"3296232","ids":",ci3296232,","sources":",ci,","types":",origin,phase-data,","nst":4,"dmin":1.101,"rms":0.64,"gap":344,"magType":"ml","type":"earthquake","title":"M 3.7 - 27km ESE of Maneadero, B.C., MX"},"geometry":{"type":"Point","coordinates":[-116.3073333,31.6203333,6]},"id":"ci3296232"},
{"type":"Feature","properties":{"mag":6.4,"place":"Kuril Islands","time":-384530181000,"updated":1594359852993,"tz":null,"url":"https://earthquake.usgs.gov/earthquakes/eventpage/iscgem887426","detail":"https://earthquake.usgs.gov/fdsnws/event/1/query?eventid=iscgem887426&format=geojson","felt":null,"cdi":null,"mmi":5.821,"alert":null,"status":"automatic","tsunami":0,"sig":630,"net":"iscgem","code":"887426","ids":",iscgem887426,","sources":",iscgem,","types":",origin,shakemap,","nst":null,"dmin":null,"rms":null,"gap":null,"magType":"mw","type":"earthquake","title":"M 6.4 - Kuril Islands"},"geometry":{"type":"Point","coordinates":[156.455,50.388,50.1]},"id":"iscgem887426"},
{"type":"Feature","properties":{"mag":6.2,"place":"Gulf of California","time":-384574528000,"updated":1594359831929,"tz":null,"url":"https://earthquake.usgs.gov/earthquakes/eventpage/iscgem887419","detail":"https://earthquake.usgs.gov/fdsnws/event/1/query?eventid=iscgem887419&format=geojson","felt":null,"cdi":null,"mmi":4.927,"alert":null,"status":"automatic","tsunami":0,"sig":591,"net":"iscgem","code":"887419","ids":",iscgem887419,","sources":",iscgem,","types":",origin,shakemap,","nst":null,"dmin":null,"rms":null,"gap":null,"magType":"mw","type":"earthquake","title":"M 6.2 - Gulf of California"},"geometry":{"type":"Point","coordinates":[-109.245,24.79,15]},"id":"iscgem887419"},
{"type":"Feature","properties":{"mag":5.3,"place":"western Turkey","time":-384643606000,"updated":1436806943000,"tz":null,"url":"https://earthquake.usgs.gov/earthquakes/eventpage/iscgemsup887416","detail":"https://earthquake.usgs.gov/fdsnws/event/1/query?eventid=iscgemsup887416&format=geojson","felt":null,"cdi":null,"mmi":null,"alert":null,"status":"automatic","tsunami":0,"sig":432,"net":"iscgemsup","code":"887416","ids":",iscgemsup887416,","sources":",iscgemsup,","types":",origin,","nst":null,"dmin":null,"rms":null,"gap":null,"magType":"mw","type":"earthquake","title":"M 5.3 - western Turkey"},"geometry":{"type":"Point","coordinates":[29.91,40.043,15]},"id":"iscgemsup887416"},
{"type":"Feature","properties":{"mag":6,"place":"Vanuatu","time":-384651736000,"updated":1594359810683,"tz":null,"url":"https://earthquake.usgs.gov/earthquakes/eventpage/iscgem887415","detail":"https://earthquake.usgs.gov/fdsnws/event/1/query?eventid=iscgem887415&format=geojson","felt":null,"cdi":null,"mmi":5.864,"alert":null,"status":"automatic","tsunami":0,"sig":554,"net":"iscgem","code":"887415","ids":",iscgem887415,","sources":",iscgem,","types":",origin,shakemap,","nst":null,"dmin":null,"rms":null,"gap":null,"magType":"mw","type":"earthquake","title":"M 6.0 - Vanuatu"},"geometry":{"type":"Point","coordinates":[168.138,-14.73,20]},"id":"iscgem887415"},
{"type":"Feature","properties":{"mag":6.2,"place":"Fox Islands, Aleutian Islands, Alaska","time":-384717783000,"updated":1557523009056,"tz":null,"url":"https://earthquake.usgs.gov/earthquakes/eventpage/iscgem887411","detail":"https://earthquake.usgs.gov/fdsnws/event/1/query?eventid=iscgem887411&format=geojson","felt":null,"cdi":null,"mmi":null,"alert":null,"status":"automatic","tsunami":0,"sig":591,"net":"iscgem","code":"887411","ids":",ushis2264,iscgem887411,","sources":",ushis,iscgem,","types":",impact-text,origin,trump-origin,","nst":null,"dmin":null,"rms":null,"gap":null,"magType":"mw","type":"earthquake","title":"M 6.2 - Fox Islands, Aleutian Islands, Alaska"},"geometry":{"type":"Point","coordinates":[-169.636,52.308,35]},"id":"iscgem887411"},
{"type":"Feature","properties":{"mag":5.6,"place":"Kuril Islands","time":-384750916000,"updated":1594359793198,"tz":null,"url":"https://earthquake.usgs.gov/earthquakes/eventpage/iscgem887408","detail":"https://earthquake.usgs.gov/fdsnws/event/1/query?eventid=iscgem887408&format=geojson","felt":null,"cdi":null,"mmi":4.614,"alert":null,"status":"automatic","tsunami":0,"sig":482,"net":"iscgem","code":"887408","ids":",iscgem887408,","sources":",iscgem,","types":",origin,shakemap,","nst":null,"dmin":null,"rms":null,"gap":null,"magType":"mw","type":"earthquake","title":"M 5.6 - Kuril Islands"},"geometry":{"type":"Point","coordinates":[146.206,43.348,35]},"id":"iscgem887408"},
{"type":"Feature","properties":{"mag":3.33,"place":"54km S of San Clemente Is. (SE tip), CA","time":-384759477180,"updated":1454004673280,"tz":null,"url":"https://earthquake.usgs.gov/earthquakes/eventpage/ci3296231","detail":"https://earthquake.usgs.gov/fdsnws/event/1/query?eventid=ci3296231&format=geojson","felt":null,"cdi":null,"mmi":null,"alert":null,"status":"reviewed","tsunami":0,"sig":171,"net":"ci","code":"3296231","ids":",ci3296231,","sources":",ci,","types":",origin,phase-data,","nst":7,"dmin":1.376,"rms":0.56,"gap":236,"magType":"ml","type":"earthquake","title":"M 3.3 - 54km S of San Clemente Is. (SE tip), CA"},"geometry":{"type":"Point","coordinates":[-118.2493333,32.3378333,6]},"id":"ci3296231"},
{"type":"Feature","properties":{"mag":3.01,"place":"15km NE of Grapevine, CA","time":-384870525250,"updated":1454005182640,"tz":null,"url":"https://earthquake.usgs.gov/earthquakes/eventpage/ci3296230","detail":"https://earthquake.usgs.gov/fdsnws/event/1/query?eventid=ci3296230&format=geojson","felt":null,"cdi":null,"mmi":null,"alert":null,"status":"reviewed","tsunami":0,"sig":139,"net":"ci","code":"3296230","ids":",ci3296230,","sources":",ci,","types":",origin,phase-data,","nst":9,"dmin":0.1775,"rms":0.6,"gap":126,"magType":"ml","type":"earthquake","title":"M 3.0 - 15km NE of Grapevine, CA"},"geometry":{"type":"Point","coordinates":[-118.81,35.0331667,2.66]},"id":"ci3296230"},
{"type":"Feature","properties":{"mag":2.12,"place":"11km NNE of Glendora, CA","time":-384892826560,"updated":1454004912260,"tz":null,"url":"https://earthquake.usgs.gov/earthquakes/eventpage/ci3296229","detail":"https://earthquake.usgs.gov/fdsnws/event/1/query?eventid=ci3296229&format=geojson","felt":null,"cdi":null,"mmi":null,"alert":null,"status":"reviewed","tsunami":0,"sig":69,"net":"ci","code":"3296229","ids":",ci3296229,","sources":",ci,","types":",origin,phase-data,","nst":4,"dmin":0.3097,"rms":0.23,"gap":223,"magType":"ml","type":"earthquake","title":"M 2.1 - 11km NNE of Glendora, CA"},"geometry":{"type":"Point","coordinates":[-117.8073333,34.2188333,6]},"id":"ci3296229"},
{"type":"Feature","properties":{"mag":6.2,"place":"northern Mid-Atlantic Ridge","time":-384954935000,"updated":1431543172000,"tz":null,"url":"https://earthquake.usgs.gov/earthquakes/eventpage/iscgem887399","detail":"https://earthquake.usgs.gov/fdsnws/event/1/query?eventid=iscgem887399&format=geojson","felt":null,"cdi":null,"mmi":null,"alert":null,"status":"automatic","tsunami":0,"sig":591,"net":"iscgem","code":"887399","ids":",iscgem887399,","sources":",iscgem,","types":",origin,","nst":null,"dmin":null,"rms":null,"gap":null,"magType":"mw","type":"earthquake","title":"M 6.2 - northern Mid-Atlantic Ridge"},"geometry":{"type":"Point","coordinates":[-42.008,10.394,15]},"id":"iscgem887399"},
{"type":"Feature","properties":{"mag":6.8,"place":"Taiwan","time":-385018262000,"updated":1594359773385,"tz":null,"url":"https://earthquake.usgs.gov/earthquakes/eventpage/iscgem887394","detail":"https://earthquake.usgs.gov/fdsnws/event/1/query?eventid=iscgem887394&format=geojson","felt":null,"cdi":null,"mmi":6.364,"alert":null,"status":"automatic","tsunami":0,"sig":711,"net":"iscgem","code":"887394","ids":",iscgem887394,","sources":",iscgem,","types":",origin,shakemap,","nst":null,"dmin":null,"rms":null,"gap":null,"magType":"mw","type":"earthquake","title":"M 6.8 - Taiwan"},"geometry":{"type":"Point","coordinates":[121.517,23.655,30]},"id":"iscgem887394"},
{"type":"Feature","properties":{"mag":3.74,"place":"74km E of Maneadero, B.C., MX","time":-385140725020,"updated":1454005497850,"tz":null,"url":"https://earthquake.usgs.gov/earthquakes/eventpage/ci3296228","detail":"https://earthquake.usgs.gov/fdsnws/event/1/query?eventid=ci3296228&format=geojson","felt":null,"cdi":null,"mmi":null,"alert":null,"status":"reviewed","tsunami":0,"sig":215,"net":"ci","code":"3296228","ids":",ci3296228,","sources":",ci,","types":",origin,phase-data,","nst":5,"dmin":1.314,"rms":0.48,"gap":296,"magType":"ml","type":"earthquake","title":"M 3.7 - 74km E of Maneadero, B.C., MX"},"geometry":{"type":"Point","coordinates":[-115.8053333,31.5875,6]},"id":"ci3296228"},
{"type":"Feature","properties":{"mag":5.1,"place":"Greece","time":-385164548000,"updated":1436806943000,"tz":null,"url":"https://earthquake.usgs.gov/earthquakes/eventpage/iscgemsup887387","detail":"https://earthquake.usgs.gov/fdsnws/event/1/query?eventid=iscgemsup887387&format=geojson","felt":null,"cdi":null,"mmi":null,"alert":null,"status":"automatic","tsunami":0,"sig":400,"net":"iscgemsup","code":"887387","ids":",iscgemsup887387,","sources":",iscgemsup,","types":",origin,","nst":null,"dmin":null,"rms":null,"gap":null,"magType":"mw","type":"earthquake","title":"M 5.1 - Greece"},"geometry":{"type":"Point","coordinates":[21.813,38.462,15]},"id":"iscgemsup887387"},
{"type":"Feature","properties":{"mag":5.3,"place":"northern Mid-Atlantic Ridge","time":-385204944000,"updated":1436806943000,"tz":null,"url":"https://earthquake.usgs.gov/earthquakes/eventpage/iscgemsup887384","detail":"https://earthquake.usgs.gov/fdsnws/event/1/query?eventid=iscgemsup887384&format=geojson","felt":null,"cdi":null,"mmi":null,"alert":null,"status":"automatic","tsunami":0,"sig":432,"net":"iscgemsup","code":"887384","ids":",iscgemsup887384,","sources":",iscgemsup,","types":",origin,","nst":null,"dmin":null,"rms":null,"gap":null,"magType":"mw","type":"earthquake","title":"M 5.3 - northern Mid-Atlantic Ridge"},"geometry":{"type":"Point","coordinates":[-27.646,46.458,15]},"id":"iscgemsup887384"},
{"type":"Feature","properties":{"mag":4.6,"place":"Nevada","time":-385220751000,"updated":1528145024000,"tz":null,"url":"https://earthquake.usgs.gov/earthquakes/eventpage/ushis2263","detail":"https://earthquake.usgs.gov/fdsnws/event/1/query?eventid=ushis2263&format=geojson","felt":null,"cdi":null,"mmi":null,"alert":null,"status":"reviewed","tsunami":0,"sig":326,"net":"ushis","code":"2263","ids":",ushis2263,","sources":",ushis,","types":",impact-text,origin,","nst":null,"dmin":null,"rms":null,"gap":null,"magType":"ml","type":"earthquake","title":"M 4.6 - Nevada"},"geometry":{"type":"Point","coordinates":[-118.43,39.28,null]},"id":"ushis2263"},
{"type":"Feature","properties":{"mag":3.52,"place":"28km WNW of Desert Center, CA","time":-385333456810,"updated":1454005454260,"tz":null,"url":"https://earthquake.usgs.gov/earthquakes/eventpage/ci3296226","detail":"https://earthquake.usgs.gov/fdsnws/event/1/query?eventid=ci3296226&format=geojson","felt":null,"cdi":null,"mmi":null,"alert":null,"status":"reviewed","tsunami":0,"sig":191,"net":"ci","code":"3296226","ids":",ci3296226,","sources":",ci,","types":",origin,phase-data,","nst":4,"dmin":0.132,"rms":0.74,"gap":251,"magType":"ml","type":"earthquake","title":"M 3.5 - 28km WNW of Desert Center, CA"},"geometry":{"type":"Point","coordinates":[-115.6706667,33.837,6]},"id":"ci3296226"},
{"type":"Feature","properties":{"mag":5.5,"place":"off the coast of Costa Rica","time":-385415866000,"updated":1431543172000,"tz":null,"url":"https://earthquake.usgs.gov/earthquakes/eventpage/iscgem887375","detail":"https://earthquake.usgs.gov/fdsnws/event/1/query?eventid=iscgem887375&format=geojson","felt":null,"cdi":null,"mmi":null,"alert":null,"status":"automatic","tsunami":0,"sig":465,"net":"iscgem","code":"887375","ids":",iscgem887375,","sources":",iscgem,","types":",origin,","nst":null,"dmin":null,"rms":null,"gap":null,"magType":"mw","type":"earthquake","title":"M 5.5 - off the coast of Costa Rica"},"geometry":{"type":"Point","coordinates":[-84.09,8.781,35]},"id":"iscgem887375"},
{"type":"Feature","properties":{"mag":6.2,"place":"west of Macquarie Island","time":-385529215000,"updated":1431543172000,"tz":null,"url":"https://earthquake.usgs.gov/earthquakes/eventpage/iscgem887368","detail":"https://earthquake.usgs.gov/fdsnws/event/1/query?eventid=iscgem887368&format=geojson","felt":null,"cdi":null,"mmi":null,"alert":null,"status":"automatic","tsunami":0,"sig":591,"net":"iscgem","code":"887368","ids":",iscgem887368,","sources":",iscgem,","types":",origin,","nst":null,"dmin":null,"rms":null,"gap":null,"magType":"mw","type":"earthquake","title":"M 6.2 - west of Macquarie Island"},"geometry":{"type":"Point","coordinates":[151.233,-60.518,15]},"id":"iscgem887368"},
{"type":"Feature","properties":{"mag":6.1,"place":"off the east coast of the Kamchatka Peninsula, Russia","time":-385587639000,"updated":1431543172000,"tz":null,"url":"https://earthquake.usgs.gov/earthquakes/eventpage/iscgem887367","detail":"https://earthquake.usgs.gov/fdsnws/event/1/query?eventid=iscgem887367&format=geojson","felt":null,"cdi":null,"mmi":null,"alert":null,"status":"automatic","tsunami":0,"sig":572,"net":"iscgem","code":"887367","ids":",iscgem887367,","sources":",iscgem,","types":",origin,","nst":null,"dmin":null,"rms":null,"gap":null,"magType":"mw","type":"earthquake","title":"M 6.1 - off the east coast of the Kamchatka Peninsula, Russia"},"geometry":{"type":"Point","coordinates":[160.278,52.426,25]},"id":"iscgem887367"},
{"type":"Feature","properties":{"mag":6,"place":"Java, Indonesia","time":-385621371000,"updated":1594359759595,"tz":null,"url":"https://earthquake.usgs.gov/earthquakes/eventpage/iscgem887365","detail":"https://earthquake.usgs.gov/fdsnws/event/1/query?eventid=iscgem887365&format=geojson","felt":null,"cdi":null,"mmi":4.093,"alert":null,"status":"automatic","tsunami":0,"sig":554,"net":"iscgem","code":"887365","ids":",iscgem887365,","sources":",iscgem,","types":",origin,shakemap,","nst":null,"dmin":null,"rms":null,"gap":null,"magType":"mw","type":"earthquake","title":"M 6.0 - Java, Indonesia"},"geometry":{"type":"Point","coordinates":[110.178,-8.317,50]},"id":"iscgem887365"},
{"type":"Feature","properties":{"mag":2.75,"place":"15km NE of Apple Valley, CA","time":-385689424540,"updated":1459570067071,"tz":null,"url":"https://earthquake.usgs.gov/earthquakes/eventpage/ci3296225","detail":"https://earthquake.usgs.gov/fdsnws/event/1/query?eventid=ci3296225&format=geojson","felt":null,"cdi":null,"mmi":null,"alert":null,"status":"reviewed","tsunami":0,"sig":116,"net":"ci","code":"3296225","ids":",ci3296225,","sources":",ci,","types":",nearby-cities,origin,phase-data,","nst":6,"dmin":0.6552,"rms":0.45,"gap":190,"magType":"ml","type":"quarry blast","title":"M 2.8 Quarry Blast - 15km NE of Apple Valley, CA"},"geometry":{"type":"Point","coordinates":[-117.074,34.6008333,0.01]},"id":"ci3296225"},
{"type":"Feature","properties":{"mag":2.85,"place":"2km NNE of Big Bear City, CA","time":-385776036890,"updated":1459593624549,"tz":null,"url":"https://earthquake.usgs.gov/earthquakes/eventpage/ci3296224","detail":"https://earthquake.usgs.gov/fdsnws/event/1/query?eventid=ci3296224&format=geojson","felt":null,"cdi":null,"mmi":null,"alert":null,"status":"reviewed","tsunami":0,"sig":125,"net":"ci","code":"3296224","ids":",ci3296224,","sources":",ci,","types":",nearby-cities,origin,phase-data,","nst":7,"dmin":0.5265,"rms":0.44,"gap":140,"magType":"ml","type":"earthquake","title":"M 2.9 - 2km NNE of Big Bear City, CA"},"geometry":{"type":"Point","coordinates":[-116.8385,34.275,6]},"id":"ci3296224"},
{"type":"Feature","properties":{"mag":5.8,"place":"Fox Islands, Aleutian Islands, Alaska","time":-385794355000,"updated":1557522863420,"tz":null,"url":"https://earthquake.usgs.gov/earthquakes/eventpage/iscgem887357","detail":"https://earthquake.usgs.gov/fdsnws/event/1/query?eventid=iscgem887357&format=geojson","felt":null,"cdi":null,"mmi":null,"alert":null,"status":"automatic","tsunami":0,"sig":518,"net":"iscgem","code":"887357","ids":",ushis2262,iscgem887357,","sources":",ushis,iscgem,","types":",impact-text,origin,trump-origin,","nst":null,"dmin":null,"rms":null,"gap":null,"magType":"mw","type":"earthquake","title":"M 5.8 - Fox Islands, Aleutian Islands, Alaska"},"geometry":{"type":"Point","coordinates":[-165.385,53.685,45]},"id":"iscgem887357"},
{"type":"Feature","properties":{"mag":3.02,"place":"13km SE of Arvin, CA","time":-385916714620,"updated":1454005453730,"tz":null,"url":"https://earthquake.usgs.gov/earthquakes/eventpage/ci3296223","detail":"https://earthquake.usgs.gov/fdsnws/event/1/query?eventid=ci3296223&format=geojson","felt":null,"cdi":null,"mmi":null,"alert":null,"status":"reviewed","tsunami":0,"sig":140,"net":"ci","code":"3296223","ids":",ci3296223,","sources":",ci,","types":",origin,phase-data,","nst":13,"dmin":0.294,"rms":0.61,"gap":97,"magType":"ml","type":"earthquake","title":"M 3.0 - 13km SE of Arvin, CA"},"geometry":{"type":"Point","coordinates":[-118.728,35.1298333,3]},"id":"ci3296223"},
{"type":"Feature","properties":{"mag":3.21,"place":"4km N of Fontana, CA","time":-385926092490,"updated":1454005744240,"tz":null,"url":"https://earthquake.usgs.gov/earthquakes/eventpage/ci3296222","detail":"https://earthquake.usgs.gov/fdsnws/event/1/query?eventid=ci3296222&format=geojson","felt":null,"cdi":null,"mmi":null,"alert":null,"status":"reviewed","tsunami":0,"sig":159,"net":"ci","code":"3296222","ids":",ci3296222,","sources":",ci,","types":",origin,phase-data,","nst":13,"dmin":null,"rms":0.72,"gap":150,"magType":"ml","type":"earthquake","title":"M 3.2 - 4km N of Fontana, CA"},"geometry":{"type":"Point","coordinates":[-117.4586667,34.1326667,6.53]},"id":"ci3296222"},
{"type":"Feature","properties":{"mag":5.3,"place":"Greece","time":-386009952000,"updated":1436806943000,"tz":null,"url":"https://earthquake.usgs.gov/earthquakes/eventpage/iscgemsup887346","detail":"https://earthquake.usgs.gov/fdsnws/event/1/query?eventid=iscgemsup887346&format=geojson","felt":null,"cdi":null,"mmi":null,"alert":null,"status":"automatic","tsunami":0,"sig":432,"net":"iscgemsup","code":"887346","ids":",iscgemsup887346,","sources":",iscgemsup,","types":",origin,","nst":null,"dmin":null,"rms":null,"gap":null,"magType":"mw","type":"earthquake","title":"M 5.3 - Greece"},"geometry":{"type":"Point","coordinates":[20.402,38.75,15]},"id":"iscgemsup887346"},
{"type":"Feature","properties":{"mag":2.41,"place":"12km NW of Castaic, CA","time":-386071589760,"updated":1454003811020,"tz":null,"url":"https://earthquake.usgs.gov/earthquakes/eventpage/ci3296220","detail":"https://earthquake.usgs.gov/fdsnws/event/1/query?eventid=ci3296220&format=geojson","felt":null,"cdi":null,"mmi":null,"alert":null,"status":"reviewed","tsunami":0,"sig":89,"net":"ci","code":"3296220","ids":",ci3296220,","sources":",ci,","types":",origin,phase-data,","nst":9,"dmin":0.3401,"rms":0.6,"gap":171,"magType":"ml","type":"earthquake","title":"M 2.4 - 12km NW of Castaic, CA"},"geometry":{"type":"Point","coordinates":[-118.7021667,34.5723333,6]},"id":"ci3296220"},
{"type":"Feature","properties":{"mag":6,"place":"off the east coast of the Kamchatka Peninsula, Russia","time":-386073608000,"updated":1431543172000,"tz":null,"url":"https://earthquake.usgs.gov/earthquakes/eventpage/iscgem887340","detail":"https://earthquake.usgs.gov/fdsnws/event/1/query?eventid=iscgem887340&format=geojson","felt":null,"cdi":null,"mmi":null,"alert":null,"status":"automatic","tsunami":0,"sig":554,"net":"iscgem","code":"887340","ids":",iscgem887340,","sources":",iscgem,","types":",origin,","nst":null,"dmin":null,"rms":null,"gap":null,"magType":"mw","type":"earthquake","title":"M 6.0 - off the east coast of the Kamchatka Peninsula, Russia"},"geometry":{"type":"Point","coordinates":[159.445,51.568,25.3]},"id":"iscgem887340"},
{"type":"Feature","properties":{"mag":1.96,"place":"3km N of Marina del Rey, CA","time":-386081165470,"updated":1454004911230,"tz":null,"url":"https://earthquake.usgs.gov/earthquakes/eventpage/ci3296219","detail":"https://earthquake.usgs.gov/fdsnws/event/1/query?eventid=ci3296219&format=geojson","felt":null,"cdi":null,"mmi":null,"alert":null,"status":"reviewed","tsunami":0,"sig":59,"net":"ci","code":"3296219","ids":",ci3296219,","sources":",ci,","types":",origin,phase-data,","nst":6,"dmin":0.2634,"rms":0.46,"gap":250,"magType":"mh","type":"earthquake","title":"M 2.0 - 3km N of Marina del Rey, CA"},"geometry":{"type":"Point","coordinates":[-118.4455,34.0091667,12.75]},"id":"ci3296219"},
{"type":"Feature","properties":{"mag":3.66,"place":"17km WSW of Tehachapi, CA","time":-386096846180,"updated":1454004629050,"tz":null,"url":"https://earthquake.usgs.gov/earthquakes/eventpage/ci3296218","detail":"https://earthquake.usgs.gov/fdsnws/event/1/query?eventid=ci3296218&format=geojson","felt":null,"cdi":null,"mmi":null,"alert":null,"status":"reviewed","tsunami":0,"sig":206,"net":"ci","code":"3296218","ids":",ci3296218,","sources":",ci,","types":",origin,phase-data,","nst":13,"dmin":0.3028,"rms":0.55,"gap":87,"magType":"ml","type":"earthquake","title":"M 3.7 - 17km WSW of Tehachapi, CA"},"geometry":{"type":"Point","coordinates":[-118.6266667,35.075,6]},"id":"ci3296218"},
{"type":"Feature","properties":{"mag":2.29,"place":"11km N of Castaic, CA","time":-386113588260,"updated":1454005182220,"tz":null,"url":"https://earthquake.usgs.gov/earthquakes/eventpage/ci3296217","detail":"https://earthquake.usgs.gov/fdsnws/event/1/query?eventid=ci3296217&format=geojson","felt":null,"cdi":null,"mmi":null,"alert":null,"status":"reviewed","tsunami":0,"sig":81,"net":"ci","code":"3296217","ids":",ci3296217,","sources":",ci,","types":",origin,phase-data,","nst":6,"dmin":0.5845,"rms":0.35,"gap":230,"magType":"mh","type":"earthquake","title":"M 2.3 - 11km N of Castaic, CA"},"geometry":{"type":"Point","coordinates":[-118.6446667,34.5833333,6]},"id":"ci3296217"},
{"type":"Feature","properties":{"mag":2.79,"place":"25km SE of Bodfish, CA","time":-386118394660,"updated":1454003810530,"tz":null,"url":"https://earthquake.usgs.gov/earthquakes/eventpage/ci3296216","detail":"https://earthquake.usgs.gov/fdsnws/event/1/query?eventid=ci3296216&format=geojson","felt":null,"cdi":null,"mmi":null,"alert":null,"status":"reviewed","tsunami":0,"sig":120,"net":"ci","code":"3296216","ids":",ci3296216,","sources":",ci,","types":",origin,phase-data,","nst":9,"dmin":0.2612,"rms":0.58,"gap":94,"magType":"ml","type":"earthquake","title":"M 2.8 - 25km SE of Bodfish, CA"},"geometry":{"type":"Point","coordinates":[-118.2658333,35.4638333,0.67]},"id":"ci3296216"},
{"type":"Feature","properties":{"mag":2.96,"place":"20km SE of Bodfish, CA","time":-386124333080,"updated":1454005453200,"tz":null,"url":"https://earthquake.usgs.gov/earthquakes/eventpage/ci3296215","detail":"https://earthquake.usgs.gov/fdsnws/event/1/query?eventid=ci3296215&format=geojson","felt":null,"cdi":null,"mmi":null,"alert":null,"status":"reviewed","tsunami":0,"sig":135,"net":"ci","code":"3296215","ids":",ci3296215,","sources":",ci,","types":",origin,phase-data,","nst":9,"dmin":0.2278,"rms":0.6,"gap":90,"magType":"ml","type":"earthquake","title":"M 3.0 - 20km SE of Bodfish, CA"},"geometry":{"type":"Point","coordinates":[-118.3166667,35.4741667,9.32]},"id":"ci3296215"},
{"type":"Feature","properties":{"mag":4.35,"place":"84km ESE of Maneadero, B.C., MX","time":-386162284690,"updated":1454005743670,"tz":null,"url":"https://earthquake.usgs.gov/earthquakes/eventpage/ci3296212","detail":"https://earthquake.usgs.gov/fdsnws/event/1/query?eventid=ci3296212&format=geojson","felt":null,"cdi":null,"mmi":null,"alert":null,"status":"reviewed","tsunami":0,"sig":291,"net":"ci","code":"3296212","ids":",ci3296212,","sources":",ci,","types":",origin,phase-data,","nst":6,"dmin":1.511,"rms":1.09,"gap":343,"magType":"ml","type":"earthquake","title":"M 4.4 - 84km ESE of Maneadero, B.C., MX"},"geometry":{"type":"Point","coordinates":[-115.771,31.3731667,6]},"id":"ci3296212"},
{"type":"Feature","properties":{"mag":6,"place":"offshore Sucre, Venezuela","time":-386204750000,"updated":1594359743528,"tz":null,"url":"https://earthquake.usgs.gov/earthquakes/eventpage/iscgem887328","detail":"https://earthquake.usgs.gov/fdsnws/event/1/query?eventid=iscgem887328&format=geojson","felt":null,"cdi":null,"mmi":5.495,"alert":null,"status":"automatic","tsunami":0,"sig":554,"net":"iscgem","code":"887328","ids":",iscgem887328,","sources":",iscgem,","types":",origin,shakemap,","nst":null,"dmin":null,"rms":null,"gap":null,"magType":"mw","type":"earthquake","title":"M 6.0 - offshore Sucre, Venezuela"},"geometry":{"type":"Point","coordinates":[-62.668,10.942,15]},"id":"iscgem887328"},
{"type":"Feature","properties":{"mag":5.5,"place":"Tajikistan","time":-386212751000,"updated":1594359727505,"tz":null,"url":"https://earthquake.usgs.gov/earthquakes/eventpage/iscgem887327","detail":"https://earthquake.usgs.gov/fdsnws/event/1/query?eventid=iscgem887327&format=geojson","felt":null,"cdi":null,"mmi":4.284,"alert":null,"status":"automatic","tsunami":0,"sig":465,"net":"iscgem","code":"887327","ids":",iscgem887327,","sources":",iscgem,","types":",origin,shakemap,","nst":null,"dmin":null,"rms":null,"gap":null,"magType":"mw","type":"earthquake","title":"M 5.5 - Tajikistan"},"geometry":{"type":"Point","coordinates":[69.446,37.538,50]},"id":"iscgem887327"},
{"type":"Feature","properties":{"mag":5.4,"place":"Crete, Greece","time":-386252592000,"updated":1436806943000,"tz":null,"url":"https://earthquake.usgs.gov/earthquakes/eventpage/iscgemsup887321","detail":"https://earthquake.usgs.gov/fdsnws/event/1/query?eventid=iscgemsup887321&format=geojson","felt":null,"cdi":null,"mmi":null,"alert":null,"status":"automatic","tsunami":0,"sig":449,"net":"iscgemsup","code":"887321","ids":",iscgemsup887321,","sources":",iscgemsup,","types":",origin,","nst":null,"dmin":null,"rms":null,"gap":null,"magType":"mw","type":"earthquake","title":"M 5.4 - Crete, Greece"},"geometry":{"type":"Point","coordinates":[26.762,34.402,15]},"id":"iscgemsup887321"},
{"type":"Feature","properties":{"mag":5.5,"place":"Rat Islands, Aleutian Islands, Alaska","time":-386294657000,"updated":1528145024000,"tz":null,"url":"https://earthquake.usgs.gov/earthquakes/eventpage/ushis2261","detail":"https://earthquake.usgs.gov/fdsnws/event/1/query?eventid=ushis2261&format=geojson","felt":null,"cdi":null,"mmi":null,"alert":null,"status":"reviewed","tsunami":0,"sig":465,"net":"ushis","code":"2261","ids":",ushis2261,","sources":",ushis,","types":",impact-text,origin,","nst":null,"dmin":null,"rms":null,"gap":null,"magType":"ms","type":"earthquake","title":"M 5.5 - Rat Islands, Aleutian Islands, Alaska"},"geometry":{"type":"Point","coordinates":[177.8,52.56,null]},"id":"ushis2261"},
{"type":"Feature","properties":{"mag":3.98,"place":"100km ESE of Maneadero, B.C., MX","time":-386307733240,"updated":1454004354910,"tz":null,"url":"https://earthquake.usgs.gov/earthquakes/eventpage/ci3296211","detail":"https://earthquake.usgs.gov/fdsnws/event/1/query?eventid=ci3296211&format=geojson","felt":null,"cdi":null,"mmi":null,"alert":null,"status":"reviewed","tsunami":0,"sig":244,"net":"ci","code":"3296211","ids":",ci3296211,","sources":",ci,","types":",origin,phase-data,","nst":5,"dmin":1.657,"rms":1.01,"gap":350,"magType":"ml","type":"earthquake","title":"M 4.0 - 100km ESE of Maneadero, B.C., MX"},"geometry":{"type":"Point","coordinates":[-115.6585,31.2598333,6]},"id":"ci3296211"},
{"type":"Feature","properties":{"mag":4.06,"place":"77km E of Maneadero, B.C., MX","time":-386310345990,"updated":1454004910730,"tz":null,"url":"https://earthquake.usgs.gov/earthquakes/eventpage/ci3296210","detail":"https://earthquake.usgs.gov/fdsnws/event/1/query?eventid=ci3296210&format=geojson","felt":null,"cdi":null,"mmi":null,"alert":null,"status":"reviewed","tsunami":0,"sig":254,"net":"ci","code":"3296210","ids":",ci3296210,","sources":",ci,","types":",origin,phase-data,","nst":5,"dmin":1.257,"rms":0.81,"gap":350,"magType":"ml","type":"earthquake","title":"M 4.1 - 77km E of Maneadero, B.C., MX"},"geometry":{"type":"Point","coordinates":[-115.75,31.6923333,6]},"id":"ci3296210"},
{"type":"Feature","properties":{"mag":3.95,"place":"18km SSW of Little Lake, CA","time":-386337562930,"updated":1454004069390,"tz":null,"url":"https://earthquake.usgs.gov/earthquakes/eventpage/ci3296209","detail":"https://earthquake.usgs.gov/fdsnws/event/1/query?eventid=ci3296209&format=geojson","felt":null,"cdi":null,"mmi":null,"alert":null,"status":"reviewed","tsunami":0,"sig":240,"net":"ci","code":"3296209","ids":",ci3296209,","sources":",ci,","types":",origin,phase-data,","nst":13,"dmin":null,"rms":0.49,"gap":91,"magType":"ml","type":"earthquake","title":"M 4.0 - 18km SSW of Little Lake, CA"},"geometry":{"type":"Point","coordinates":[-118.0205,35.7981667,6]},"id":"ci3296209"},
{"type":"Feature","properties":{"mag":6.4,"place":"offshore Sucre, Venezuela","time":-386361231000,"updated":1594359698686,"tz":null,"url":"https://earthquake.usgs.gov/earthquakes/eventpage/iscgem887303","detail":"https://earthquake.usgs.gov/fdsnws/event/1/query?eventid=iscgem887303&format=geojson","felt":null,"cdi":null,"mmi":6.279,"alert":null,"status":"automatic","tsunami":0,"sig":630,"net":"iscgem","code":"887303","ids":",iscgem887303,","sources":",iscgem,","types":",origin,shakemap,","nst":null,"dmin":null,"rms":null,"gap":null,"magType":"mw","type":"earthquake","title":"M 6.4 - offshore Sucre, Venezuela"},"geometry":{"type":"Point","coordinates":[-62.706,10.824,23.3]},"id":"iscgem887303"},
{"type":"Feature","properties":{"mag":3.74,"place":"29km ESE of Maneadero, B.C., MX","time":-386361893370,"updated":1454005743160,"tz":null,"url":"https://earthquake.usgs.gov/earthquakes/eventpage/ci3296208","detail":"https://earthquake.usgs.gov/fdsnws/event/1/query?eventid=ci3296208&format=geojson","felt":null,"cdi":null,"mmi":null,"alert":null,"status":"reviewed","tsunami":0,"sig":215,"net":"ci","code":"3296208","ids":",ci3296208,","sources":",ci,","types":",origin,phase-data,","nst":4,"dmin":1.073,"rms":0.75,"gap":344,"magType":"ml","type":"earthquake","title":"M 3.7 - 29km ESE of Maneadero, B.C., MX"},"geometry":{"type":"Point","coordinates":[-116.2683333,31.66,6]},"id":"ci3296208"},
{"type":"Feature","properties":{"mag":3.29,"place":"26km NE of Arvin, CA","time":-386424940200,"updated":1454004068850,"tz":null,"url":"https://earthquake.usgs.gov/earthquakes/eventpage/ci3296207","detail":"https://earthquake.usgs.gov/fdsnws/event/1/query?eventid=ci3296207&format=geojson","felt":null,"cdi":null,"mmi":null,"alert":null,"status":"reviewed","tsunami":0,"sig":167,"net":"ci","code":"3296207","ids":",ci3296207,","sources":",ci,","types":",origin,phase-data,","nst":11,"dmin":0.3106,"rms":0.59,"gap":80,"magType":"ml","type":"earthquake","title":"M 3.3 - 26km NE of Arvin, CA"},"geometry":{"type":"Point","coordinates":[-118.6376667,35.3816667,6]},"id":"ci3296207"},
{"type":"Feature","properties":{"mag":5.9,"place":"Chagos Archipelago region","time":-386478076000,"updated":1431543172000,"tz":null,"url":"https://earthquake.usgs.gov/earthquakes/eventpage/iscgem887294","detail":"https://earthquake.usgs.gov/fdsnws/event/1/query?eventid=iscgem887294&format=geojson","felt":null,"cdi":null,"mmi":null,"alert":null,"status":"automatic","tsunami":0,"sig":536,"net":"iscgem","code":"887294","ids":",iscgem887294,","sources":",iscgem,","types":",origin,","nst":null,"dmin":null,"rms":null,"gap":null,"magType":"mw","type":"earthquake","title":"M 5.9 - Chagos Archipelago region"},"geometry":{"type":"Point","coordinates":[69.688,-6.319,15]},"id":"iscgem887294"},
{"type":"Feature","properties":{"mag":5.9,"place":"offshore Sucre, Venezuela","time":-386508722000,"updated":1594359682535,"tz":null,"url":"https://earthquake.usgs.gov/earthquakes/eventpage/iscgem887289","detail":"https://earthquake.usgs.gov/fdsnws/event/1/query?eventid=iscgem887289&format=geojson","felt":null,"cdi":null,"mmi":5.478,"alert":null,"status":"automatic","tsunami":0,"sig":536,"net":"iscgem","code":"887289","ids":",iscgem887289,","sources":",iscgem,","types":",origin,shakemap,","nst":null,"dmin":null,"rms":null,"gap":null,"magType":"mw","type":"earthquake","title":"M 5.9 - offshore Sucre, Venezuela"},"geometry":{"type":"Point","coordinates":[-62.665,10.927,15]},"id":"iscgem887289"},
{"type":"Feature","properties":{"mag":2.97,"place":"23km ESE of Lake Isabella, CA","time":-386582544150,"updated":1454004068360,"tz":null,"url":"https://earthquake.usgs.gov/earthquakes/eventpage/ci3296206","detail":"https://earthquake.usgs.gov/fdsnws/event/1/query?eventid=ci3296206&format=geojson","felt":null,"cdi":null,"mmi":null,"alert":null,"status":"reviewed","tsunami":0,"sig":136,"net":"ci","code":"3296206","ids":",ci3296206,","sources":",ci,","types":",origin,phase-data,","nst":5,"dmin":0.5143,"rms":0.44,"gap":223,"magType":"ml","type":"earthquake","title":"M 3.0 - 23km ESE of Lake Isabella, CA"},"geometry":{"type":"Point","coordinates":[-118.2538333,35.5176667,6]},"id":"ci3296206"},
{"type":"Feature","properties":{"mag":4.02,"place":"16km ENE of Morgan Hill, CA","time":-386593449550,"updated":1454003810030,"tz":null,"url":"https://earthquake.usgs.gov/earthquakes/eventpage/ci3296205","detail":"https://earthquake.usgs.gov/fdsnws/event/1/query?eventid=ci3296205&format=geojson","felt":null,"cdi":null,"mmi":null,"alert":null,"status":"reviewed","tsunami":0,"sig":249,"net":"ci","code":"3296205","ids":",ci3296205,","sources":",ci,","types":",origin,phase-data,","nst":5,"dmin":2.341,"rms":0.75,"gap":333,"magType":"ml","type":"earthquake","title":"M 4.0 - 16km ENE of Morgan Hill, CA"},"geometry":{"type":"Point","coordinates":[-121.4965,37.1951667,6]},"id":"ci3296205"}],"bbox":[-169.636,-60.518,0.01,177.8,55.75,147.8]}