{"type":"FeatureCollection","metadata":{"generated":1597556320000,"url":"https://earthquake.usgs.gov/fdsnws/event/1/query?format=geojson&starttime=1963-8-01&endtime=1963-8-31","title":"USGS Earthquakes","status":200,"api":"1.10.3","count":140},"features":[{"type":"Feature","properties":{"mag":2.12,"place":"Hawaii region, Hawaii","time":-200026870610,"updated":1585675026990,"tz":null,"url":"https://earthquake.usgs.gov/earthquakes/eventpage/hv19630801","detail":"https://earthquake.usgs.gov/fdsnws/event/1/query?eventid=hv19630801&format=geojson","felt":null,"cdi":null,"mmi":null,"alert":null,"status":"reviewed","tsunami":0,"sig":69,"net":"hv","code":"19630801","ids":",hv19630801,","sources":",hv,","types":",origin,phase-data,","nst":9,"dmin":null,"rms":0.1,"gap":191,"magType":"ml","type":"earthquake","title":"M 2.1 - Hawaii region, Hawaii"},"geometry":{"type":"Point","coordinates":[-155.207,19.318,5.363]},"id":"hv19630801"},
{"type":"Feature","properties":{"mag":3.03,"place":"10km E of Joshua Tree, CA","time":-200061535730,"updated":1454011042350,"tz":null,"url":"https://earthquake.usgs.gov/earthquakes/eventpage/ci3331207","detail":"https://earthquake.usgs.gov/fdsnws/event/1/query?eventid=ci3331207&format=geojson","felt":null,"cdi":null,"mmi":null,"alert":null,"status":"reviewed","tsunami":0,"sig":141,"net":"ci","code":"3331207","ids":",ci3331207,","sources":",ci,","types":",origin,phase-data,","nst":7,"dmin":0.648,"rms":0.56,"gap":185,"magType":"ml","type":"earthquake","title":"M 3.0 - 10km E of Joshua Tree, CA"},"geometry":{"type":"Point","coordinates":[-116.2108333,34.1486667,6]},"id":"ci3331207"},
{"type":"Feature","properties":{"mag":2.96,"place":"5km WSW of Volcano, Hawaii","time":-200076559540,"updated":1585675026770,"tz":-600,"url":"https://earthquake.usgs.gov/earthquakes/eventpage/hv19630800","detail":"https://earthquake.usgs.gov/fdsnws/event/1/query?eventid=hv19630800&format=geojson","felt":null,"cdi":null,"mmi":null,"alert":null,"status":"reviewed","tsunami":0,"sig":135,"net":"hv","code":"19630800","ids":",hv19630800,","sources":",hv,","types":",geoserve,origin,phase-data,","nst":10,"dmin":null,"rms":0.11,"gap":81,"magType":"ml","type":"earthquake","title":"M 3.0 - 5km WSW of Volcano, Hawaii"},"geometry":{"type":"Point","coordinates":[-155.2878333,19.4051667,28.783]},"id":"hv19630800"},
{"type":"Feature","properties":{"mag":5.6,"place":"Kazakhstan-Xinjiang border region","time":-200085217000,"updated":1431543177000,"tz":null,"url":"https://earthquake.usgs.gov/earthquakes/eventpage/iscgem872993","detail":"https://earthquake.usgs.gov/fdsnws/event/1/query?eventid=iscgem872993&format=geojson","felt":null,"cdi":null,"mmi":null,"alert":null,"status":"automatic","tsunami":0,"sig":482,"net":"iscgem","code":"872993","ids":",iscgem872993,","sources":",iscgem,","types":",origin,","nst":null,"dmin":null,"rms":null,"gap":null,"magType":"mw","type":"earthquake","title":"M 5.6 - Kazakhstan-Xinjiang border region"},"geometry":{"type":"Point","coordinates":[80.003,44.809,15]},"id":"iscgem872993"},
{"type":"Feature","properties":{"mag":5.8,"place":"Tonga","time":-200113347000,"updated":1431543177000,"tz":null,"url":"https://earthquake.usgs.gov/earthquakes/eventpage/iscgem872992","detail":"https://earthquake.usgs.gov/fdsnws/event/1/query?eventid=iscgem872992&format=geojson","felt":null,"cdi":null,"mmi":null,"alert":null,"status":"automatic","tsunami":0,"sig":518,"net":"iscgem","code":"872992","ids":",iscgem872992,","sources":",iscgem,","types":",origin,","nst":null,"dmin":null,"rms":null,"gap":null,"magType":"mw","type":"earthquake","title":"M 5.8 - Tonga"},"geometry":{"type":"Point","coordinates":[-173.183,-15.51,25]},"id":"iscgem872992"},
{"type":"Feature","properties":{"mag":6.6,"place":"off the coast of northern Peru","time":-200132966000,"updated":1431543177000,"tz":null,"url":"https://earthquake.usgs.gov/earthquakes/eventpage/iscgem17294187","detail":"https://earthquake.usgs.gov/fdsnws/event/1/query?eventid=iscgem17294187&format=geojson","felt":null,"cdi":null,"mmi":null,"alert":null,"status":"automatic","tsunami":0,"sig":670,"net":"iscgem","code":"17294187","ids":",iscgem17294187,","sources":",iscgem,","types":",origin,","nst":null,"dmin":null,"rms":null,"gap":null,"magType":"mw","type":"earthquake","title":"M 6.6 - off the coast of northern Peru"},"geometry":{"type":"Point","coordinates":[-81.427,-7.095,25]},"id":"iscgem17294187"},
{"type":"Feature","properties":{"mag":3.02,"place":"Hawaii region, Hawaii","time":-200148796500,"updated":1585675026560,"tz":null,"url":"https://earthquake.usgs.gov/earthquakes/eventpage/hv19630799","detail":"https://earthquake.usgs.gov/fdsnws/event/1/query?eventid=hv19630799&format=geojson","felt":null,"cdi":null,"mmi":null,"alert":null,"status":"reviewed","tsunami":0,"sig":140,"net":"hv","code":"19630799","ids":",hv19630799,","sources":",hv,","types":",origin,phase-data,","nst":10,"dmin":null,"rms":0.12,"gap":77,"magType":"ml","type":"earthquake","title":"M 3.0 - Hawaii region, Hawaii"},"geometry":{"type":"Point","coordinates":[-155.2711667,19.3825,27.093]},"id":"hv19630799"},
{"type":"Feature","properties":{"mag":6.5,"place":"southern Xinjiang, China","time":-200156772000,"updated":1594351306192,"tz":null,"url":"https://earthquake.usgs.gov/earthquakes/eventpage/iscgem872989","detail":"https://earthquake.usgs.gov/fdsnws/event/1/query?eventid=iscgem872989&format=geojson","felt":null,"cdi":null,"mmi":6.599,"alert":null,"status":"automatic","tsunami":0,"sig":650,"net":"iscgem","code":"872989","ids":",iscgem872989,","sources":",iscgem,","types":",origin,shakemap,","nst":null,"dmin":null,"rms":null,"gap":null,"magType":"mw","type":"earthquake","title":"M 6.5 - southern Xinjiang, China"},"geometry":{"type":"Point","coordinates":[74.211,39.688,15]},"id":"iscgem872989"},
{"type":"Feature","properties":{"mag":3.34,"place":"Hawaii region, Hawaii","time":-200218079060,"updated":1585675026350,"tz":null,"url":"https://earthquake.usgs.gov/earthquakes/eventpage/hv19630798","detail":"https://earthquake.usgs.gov/fdsnws/event/1/query?eventid=hv19630798&format=geojson","felt":null,"cdi":null,"mmi":null,"alert":null,"status":"reviewed","tsunami":0,"sig":172,"net":"hv","code":"19630798","ids":",hv19630798,","sources":",hv,","types":",origin,phase-data,","nst":10,"dmin":null,"rms":0.17,"gap":233,"magType":"ml","type":"earthquake","title":"M 3.3 - Hawaii region, Hawaii"},"geometry":{"type":"Point","coordinates":[-155.3095,19.0586667,13.166]},"id":"hv19630798"},
{"type":"Feature","properties":{"mag":null,"place":"Hawaii region, Hawaii","time":-200218433220,"updated":1585675026180,"tz":null,"url":"https://earthquake.usgs.gov/earthquakes/eventpage/hv19630797","detail":"https://earthquake.usgs.gov/fdsnws/event/1/query?eventid=hv19630797&format=geojson","felt":null,"cdi":null,"mmi":null,"alert":null,"status":"reviewed","tsunami":0,"sig":0,"net":"hv","code":"19630797","ids":",hv19630797,","sources":",hv,","types":",origin,phase-data,","nst":3,"dmin":null,"rms":0.14,"gap":271,"magType":null,"type":"earthquake","title":"M ? - Hawaii region, Hawaii"},"geometry":{"type":"Point","coordinates":[-155.257,18.9865,6.258]},"id":"hv19630797"},
{"type":"Feature","properties":{"mag":null,"place":"Hawaii region, Hawaii","time":-200218481810,"updated":1585675026040,"tz":null,"url":"https://earthquake.usgs.gov/earthquakes/eventpage/hv19630796","detail":"https://earthquake.usgs.gov/fdsnws/event/1/query?eventid=hv19630796&format=geojson","felt":null,"cdi":null,"mmi":null,"alert":null,"status":"reviewed","tsunami":0,"sig":0,"net":"hv","code":"19630796","ids":",hv19630796,","sources":",hv,","types":",origin,phase-data,","nst":3,"dmin":null,"rms":0.2,"gap":305,"magType":null,"type":"earthquake","title":"M ? - Hawaii region, Hawaii"},"geometry":{"type":"Point","coordinates":[-155.811,19.4823333,6.212]},"id":"hv19630796"},
{"type":"Feature","properties":{"mag":null,"place":"Hawaii region, Hawaii","time":-200218857180,"updated":1585675025910,"tz":null,"url":"https://earthquake.usgs.gov/earthquakes/eventpage/hv19630795","detail":"https://earthquake.usgs.gov/fdsnws/event/1/query?eventid=hv19630795&format=geojson","felt":null,"cdi":null,"mmi":null,"alert":null,"status":"reviewed","tsunami":0,"sig":0,"net":"hv","code":"19630795","ids":",hv19630795,","sources":",hv,","types":",origin,phase-data,","nst":4,"dmin":null,"rms":0.01,"gap":171,"magType":null,"type":"other event","title":"M ? Other Event - Hawaii region, Hawaii"},"geometry":{"type":"Point","coordinates":[-155.4796667,19.1835,48.748]},"id":"hv19630795"},
{"type":"Feature","properties":{"mag":2.99,"place":"Hawaii region, Hawaii","time":-200220356560,"updated":1585675025770,"tz":null,"url":"https://earthquake.usgs.gov/earthquakes/eventpage/hv19630794","detail":"https://earthquake.usgs.gov/fdsnws/event/1/query?eventid=hv19630794&format=geojson","felt":null,"cdi":null,"mmi":null,"alert":null,"status":"reviewed","tsunami":0,"sig":138,"net":"hv","code":"19630794","ids":",hv19630794,","sources":",hv,","types":",origin,phase-data,","nst":5,"dmin":null,"rms":0.17,"gap":321,"magType":"ml","type":"earthquake","title":"M 3.0 - Hawaii region, Hawaii"},"geometry":{"type":"Point","coordinates":[-156.085,19.6031667,5.788]},"id":"hv19630794"},
{"type":"Feature","properties":{"mag":2.8,"place":"6km WSW of El Segundo, CA","time":-200230997540,"updated":1454010528500,"tz":null,"url":"https://earthquake.usgs.gov/earthquakes/eventpage/ci3331206","detail":"https://earthquake.usgs.gov/fdsnws/event/1/query?eventid=ci3331206&format=geojson","felt":null,"cdi":null,"mmi":null,"alert":null,"status":"reviewed","tsunami":0,"sig":121,"net":"ci","code":"3331206","ids":",ci3331206,","sources":",ci,","types":",origin,phase-data,","nst":10,"dmin":0.3499,"rms":0.69,"gap":123,"magType":"ml","type":"earthquake","title":"M 2.8 - 6km WSW of El Segundo, CA"},"geometry":{"type":"Point","coordinates":[-118.473,33.9036667,0]},"id":"ci3331206"},
{"type":"Feature","properties":{"mag":1.99,"place":"2km E of Beverly Hills, CA","time":-200250179880,"updated":1454009996660,"tz":null,"url":"https://earthquake.usgs.gov/earthquakes/eventpage/ci3331205","detail":"https://earthquake.usgs.gov/fdsnws/event/1/query?eventid=ci3331205&format=geojson","felt":null,"cdi":null,"mmi":null,"alert":null,"status":"reviewed","tsunami":0,"sig":61,"net":"ci","code":"3331205","ids":",ci3331205,","sources":",ci,","types":",origin,phase-data,","nst":4,"dmin":0.1873,"rms":0.56,"gap":252,"magType":"mh","type":"earthquake","title":"M 2.0 - 2km E of Beverly Hills, CA"},"geometry":{"type":"Point","coordinates":[-118.3795,34.0761667,0.01]},"id":"ci3331205"},
{"type":"Feature","properties":{"mag":2.99,"place":"Hawaii region, Hawaii","time":-200256749090,"updated":1585675025630,"tz":null,"url":"https://earthquake.usgs.gov/earthquakes/eventpage/hv19630793","detail":"https://earthquake.usgs.gov/fdsnws/event/1/query?eventid=hv19630793&format=geojson","felt":null,"cdi":null,"mmi":null,"alert":null,"status":"reviewed","tsunami":0,"sig":138,"net":"hv","code":"19630793","ids":",hv19630793,","sources":",hv,","types":",origin,phase-data,","nst":8,"dmin":null,"rms":0.08,"gap":241,"magType":"ml","type":"earthquake","title":"M 3.0 - Hawaii region, Hawaii"},"geometry":{"type":"Point","coordinates":[-155.6096667,19.388,-0.362]},"id":"hv19630793"},
{"type":"Feature","properties":{"mag":2.42,"place":"Hawaii region, Hawaii","time":-200274571810,"updated":1585675025470,"tz":null,"url":"https://earthquake.usgs.gov/earthquakes/eventpage/hv19630792","detail":"https://earthquake.usgs.gov/fdsnws/event/1/query?eventid=hv19630792&format=geojson","felt":null,"cdi":null,"mmi":null,"alert":null,"status":"reviewed","tsunami":0,"sig":90,"net":"hv","code":"19630792","ids":",hv19630792,","sources":",hv,","types":",origin,phase-data,","nst":8,"dmin":null,"rms":0.11,"gap":158,"magType":"ml","type":"earthquake","title":"M 2.4 - Hawaii region, Hawaii"},"geometry":{"type":"Point","coordinates":[-155.4026667,19.3783333,1.178]},"id":"hv19630792"},
{"type":"Feature","properties":{"mag":2.2,"place":"Hawaii region, Hawaii","time":-200277159810,"updated":1585675025320,"tz":null,"url":"https://earthquake.usgs.gov/earthquakes/eventpage/hv19630791","detail":"https://earthquake.usgs.gov/fdsnws/event/1/query?eventid=hv19630791&format=geojson","felt":null,"cdi":null,"mmi":null,"alert":null,"status":"reviewed","tsunami":0,"sig":74,"net":"hv","code":"19630791","ids":",hv19630791,","sources":",hv,","types":",origin,phase-data,","nst":5,"dmin":null,"rms":0.04,"gap":222,"magType":"ml","type":"earthquake","title":"M 2.2 - Hawaii region, Hawaii"},"geometry":{"type":"Point","coordinates":[-155.402,19.355,6.419]},"id":"hv19630791"},
{"type":"Feature","properties":{"mag":2.89,"place":"14km WSW of Volcano, Hawaii","time":-200277982040,"updated":1585675025180,"tz":-600,"url":"https://earthquake.usgs.gov/earthquakes/eventpage/hv19630790","detail":"https://earthquake.usgs.gov/fdsnws/event/1/query?eventid=hv19630790&format=geojson","felt":null,"cdi":null,"mmi":null,"alert":null,"status":"reviewed","tsunami":0,"sig":128,"net":"hv","code":"19630790","ids":",hv19630790,","sources":",hv,","types":",geoserve,origin,phase-data,","nst":9,"dmin":null,"rms":0.06,"gap":181,"magType":"ml","type":"earthquake","title":"M 2.9 - 14km WSW of Volcano, Hawaii"},"geometry":{"type":"Point","coordinates":[-155.3601667,19.3716667,-0.643]},"id":"hv19630790"},
{"type":"Feature","properties":{"mag":2.54,"place":"Hawaii region, Hawaii","time":-200317196680,"updated":1585675025040,"tz":null,"url":"https://earthquake.usgs.gov/earthquakes/eventpage/hv19630789","detail":"https://earthquake.usgs.gov/fdsnws/event/1/query?eventid=hv19630789&format=geojson","felt":null,"cdi":null,"mmi":null,"alert":null,"status":"reviewed","tsunami":0,"sig":99,"net":"hv","code":"19630789","ids":",hv19630789,","sources":",hv,","types":",origin,phase-data,","nst":6,"dmin":null,"rms":0.12,"gap":312,"magType":"ml","type":"earthquake","title":"M 2.5 - Hawaii region, Hawaii"},"geometry":{"type":"Point","coordinates":[-155.4638333,19.3021667,1.321]},"id":"hv19630789"},
{"type":"Feature","properties":{"mag":1.8,"place":"Hawaii region, Hawaii","time":-200317328870,"updated":1585675024880,"tz":null,"url":"https://earthquake.usgs.gov/earthquakes/eventpage/hv19630788","detail":"https://earthquake.usgs.gov/fdsnws/event/1/query?eventid=hv19630788&format=geojson","felt":null,"cdi":null,"mmi":null,"alert":null,"status":"reviewed","tsunami":0,"sig":50,"net":"hv","code":"19630788","ids":",hv19630788,","sources":",hv,","types":",origin,phase-data,","nst":5,"dmin":null,"rms":0.08,"gap":285,"magType":"ml","type":"earthquake","title":"M 1.8 - Hawaii region, Hawaii"},"geometry":{"type":"Point","coordinates":[-155.4038333,19.3516667,6.047]},"id":"hv19630788"},
{"type":"Feature","properties":{"mag":1.9,"place":"Hawaii region, Hawaii","time":-200318441660,"updated":1585675024740,"tz":null,"url":"https://earthquake.usgs.gov/earthquakes/eventpage/hv19630787","detail":"https://earthquake.usgs.gov/fdsnws/event/1/query?eventid=hv19630787&format=geojson","felt":null,"cdi":null,"mmi":null,"alert":null,"status":"reviewed","tsunami":0,"sig":56,"net":"hv","code":"19630787","ids":",hv19630787,","sources":",hv,","types":",origin,phase-data,","nst":5,"dmin":null,"rms":0.04,"gap":287,"magType":"ml","type":"earthquake","title":"M 1.9 - Hawaii region, Hawaii"},"geometry":{"type":"Point","coordinates":[-155.3981667,19.3443333,5.841]},"id":"hv19630787"},
{"type":"Feature","properties":{"mag":2.54,"place":"9km SW of Thousand Oaks, CA","time":-200327290110,"updated":1454009496130,"tz":null,"url":"https://earthquake.usgs.gov/earthquakes/eventpage/ci3331204","detail":"https://earthquake.usgs.gov/fdsnws/event/1/query?eventid=ci3331204&format=geojson","felt":null,"cdi":null,"mmi":null,"alert":null,"status":"reviewed","tsunami":0,"sig":99,"net":"ci","code":"3331204","ids":",ci3331204,","sources":",ci,","types":",origin,phase-data,","nst":6,"dmin":0.6311,"rms":0.59,"gap":249,"magType":"ml","type":"earthquake","title":"M 2.5 - 9km SW of Thousand Oaks, CA"},"geometry":{"type":"Point","coordinates":[-118.9315,34.1241667,6]},"id":"ci3331204"},
{"type":"Feature","properties":{"mag":2.19,"place":"Hawaii region, Hawaii","time":-200331748450,"updated":1585675024590,"tz":null,"url":"https://earthquake.usgs.gov/earthquakes/eventpage/hv19630786","detail":"https://earthquake.usgs.gov/fdsnws/event/1/query?eventid=hv19630786&format=geojson","felt":null,"cdi":null,"mmi":null,"alert":null,"status":"reviewed","tsunami":0,"sig":74,"net":"hv","code":"19630786","ids":",hv19630786,","sources":",hv,","types":",origin,phase-data,","nst":8,"dmin":null,"rms":0.06,"gap":197,"magType":"ml","type":"earthquake","title":"M 2.2 - Hawaii region, Hawaii"},"geometry":{"type":"Point","coordinates":[-155.4831667,19.3635,9.338]},"id":"hv19630786"},
{"type":"Feature","properties":{"mag":3.47,"place":"16km N of Pahala, Hawaii","time":-200334300260,"updated":1585675023830,"tz":-600,"url":"https://earthquake.usgs.gov/earthquakes/eventpage/hv19630785","detail":"https://earthquake.usgs.gov/fdsnws/event/1/query?eventid=hv19630785&format=geojson","felt":null,"cdi":null,"mmi":null,"alert":null,"status":"reviewed","tsunami":0,"sig":185,"net":"hv","code":"19630785","ids":",hv19630785,","sources":",hv,","types":",geoserve,origin,phase-data,","nst":9,"dmin":null,"rms":0.09,"gap":297,"magType":"ml","type":"earthquake","title":"M 3.5 - 16km N of Pahala, Hawaii"},"geometry":{"type":"Point","coordinates":[-155.5023333,19.3561667,10.098]},"id":"hv19630785"},
{"type":"Feature","properties":{"mag":2.73,"place":"16km WSW of Volcano, Hawaii","time":-200340939980,"updated":1585675023450,"tz":-600,"url":"https://earthquake.usgs.gov/earthquakes/eventpage/hv19630784","detail":"https://earthquake.usgs.gov/fdsnws/event/1/query?eventid=hv19630784&format=geojson","felt":null,"cdi":null,"mmi":null,"alert":null,"status":"reviewed","tsunami":0,"sig":115,"net":"hv","code":"19630784","ids":",hv19630784,","sources":",hv,","types":",geoserve,origin,phase-data,","nst":8,"dmin":null,"rms":0.18,"gap":148,"magType":"ml","type":"earthquake","title":"M 2.7 - 16km WSW of Volcano, Hawaii"},"geometry":{"type":"Point","coordinates":[-155.3831667,19.3875,-1.164]},"id":"hv19630784"},
{"type":"Feature","properties":{"mag":2.19,"place":"Hawaii region, Hawaii","time":-200341546970,"updated":1585675023300,"tz":null,"url":"https://earthquake.usgs.gov/earthquakes/eventpage/hv19630783","detail":"https://earthquake.usgs.gov/fdsnws/event/1/query?eventid=hv19630783&format=geojson","felt":null,"cdi":null,"mmi":null,"alert":null,"status":"reviewed","tsunami":0,"sig":74,"net":"hv","code":"19630783","ids":",hv19630783,","sources":",hv,","types":",origin,phase-data,","nst":7,"dmin":null,"rms":0.26,"gap":167,"magType":"ml","type":"earthquake","title":"M 2.2 - Hawaii region, Hawaii"},"geometry":{"type":"Point","coordinates":[-155.42,19.37,0.839]},"id":"hv19630783"},
{"type":"Feature","properties":{"mag":2.29,"place":"16km N of Pahala, Hawaii","time":-200341895910,"updated":1585675023130,"tz":-600,"url":"https://earthquake.usgs.gov/earthquakes/eventpage/hv19630782","detail":"https://earthquake.usgs.gov/fdsnws/event/1/query?eventid=hv19630782&format=geojson","felt":null,"cdi":null,"mmi":null,"alert":null,"status":"reviewed","tsunami":0,"sig":81,"net":"hv","code":"19630782","ids":",hv19630782,","sources":",hv,","types":",geoserve,origin,phase-data,","nst":8,"dmin":null,"rms":0.09,"gap":304,"magType":"ml","type":"earthquake","title":"M 2.3 - 16km N of Pahala, Hawaii"},"geometry":{"type":"Point","coordinates":[-155.4701667,19.358,1.738]},"id":"hv19630782"},
{"type":"Feature","properties":{"mag":2.18,"place":"Hawaii region, Hawaii","time":-200344663870,"updated":1585675022920,"tz":null,"url":"https://earthquake.usgs.gov/earthquakes/eventpage/hv19630781","detail":"https://earthquake.usgs.gov/fdsnws/event/1/query?eventid=hv19630781&format=geojson","felt":null,"cdi":null,"mmi":null,"alert":null,"status":"reviewed","tsunami":0,"sig":73,"net":"hv","code":"19630781","ids":",hv19630781,","sources":",hv,","types":",origin,phase-data,","nst":6,"dmin":null,"rms":0.13,"gap":146,"magType":"ml","type":"earthquake","title":"M 2.2 - Hawaii region, Hawaii"},"geometry":{"type":"Point","coordinates":[-155.385,19.3511667,1.201]},"id":"hv19630781"},
{"type":"Feature","properties":{"mag":2.22,"place":"Hawaii region, Hawaii","time":-200346174060,"updated":1585675022760,"tz":null,"url":"https://earthquake.usgs.gov/earthquakes/eventpage/hv19630780","detail":"https://earthquake.usgs.gov/fdsnws/event/1/query?eventid=hv19630780&format=geojson","felt":null,"cdi":null,"mmi":null,"alert":null,"status":"reviewed","tsunami":0,"sig":76,"net":"hv","code":"19630780","ids":",hv19630780,","sources":",hv,","types":",origin,phase-data,","nst":7,"dmin":null,"rms":0.17,"gap":193,"magType":"ml","type":"earthquake","title":"M 2.2 - Hawaii region, Hawaii"},"geometry":{"type":"Point","coordinates":[-155.3946667,19.3913333,-1.252]},"id":"hv19630780"},
{"type":"Feature","properties":{"mag":6.1,"place":"off the coast of Aisen, Chile","time":-200349387000,"updated":1431543177000,"tz":null,"url":"https://earthquake.usgs.gov/earthquakes/eventpage/iscgem872979","detail":"https://earthquake.usgs.gov/fdsnws/event/1/query?eventid=iscgem872979&format=geojson","felt":null,"cdi":null,"mmi":null,"alert":null,"status":"automatic","tsunami":0,"sig":572,"net":"iscgem","code":"872979","ids":",iscgem872979,","sources":",iscgem,","types":",origin,","nst":null,"dmin":null,"rms":null,"gap":null,"magType":"mw","type":"earthquake","title":"M 6.1 - off the coast of Aisen, Chile"},"geometry":{"type":"Point","coordinates":[-76.572,-45.936,15]},"id":"iscgem872979"},
{"type":"Feature","properties":{"mag":2.43,"place":"Hawaii region, Hawaii","time":-200356521510,"updated":1585675022620,"tz":null,"url":"https://earthquake.usgs.gov/earthquakes/eventpage/hv19630779","detail":"https://earthquake.usgs.gov/fdsnws/event/1/query?eventid=hv19630779&format=geojson","felt":null,"cdi":null,"mmi":null,"alert":null,"status":"reviewed","tsunami":0,"sig":91,"net":"hv","code":"19630779","ids":",hv19630779,","sources":",hv,","types":",origin,phase-data,","nst":7,"dmin":null,"rms":0.17,"gap":163,"magType":"ml","type":"earthquake","title":"M 2.4 - Hawaii region, Hawaii"},"geometry":{"type":"Point","coordinates":[-155.4116667,19.3685,0.191]},"id":"hv19630779"},
{"type":"Feature","properties":{"mag":4.08,"place":"36km ENE of Maneadero, B.C., MX","time":-200356741980,"updated":1454011307620,"tz":null,"url":"https://earthquake.usgs.gov/earthquakes/eventpage/ci3331203","detail":"https://earthquake.usgs.gov/fdsnws/event/1/query?eventid=ci3331203&format=geojson","felt":null,"cdi":null,"mmi":null,"alert":null,"status":"reviewed","tsunami":0,"sig":256,"net":"ci","code":"3331203","ids":",ci3331203,","sources":",ci,","types":",origin,phase-data,","nst":9,"dmin":null,"rms":0.72,"gap":270,"magType":"ml","type":"earthquake","title":"M 4.1 - 36km ENE of Maneadero, B.C., MX"},"geometry":{"type":"Point","coordinates":[-116.2015,31.8091667,6]},"id":"ci3331203"},
{"type":"Feature","properties":{"mag":1.96,"place":"Hawaii region, Hawaii","time":-200362337840,"updated":1585675022490,"tz":null,"url":"https://earthquake.usgs.gov/earthquakes/eventpage/hv19630778","detail":"https://earthquake.usgs.gov/fdsnws/event/1/query?eventid=hv19630778&format=geojson","felt":null,"cdi":null,"mmi":null,"alert":null,"status":"reviewed","tsunami":0,"sig":59,"net":"hv","code":"19630778","ids":",hv19630778,","sources":",hv,","types":",origin,phase-data,","nst":5,"dmin":null,"rms":0.08,"gap":289,"magType":"ml","type":"earthquake","title":"M 2.0 - Hawaii region, Hawaii"},"geometry":{"type":"Point","coordinates":[-155.4045,19.3425,5.881]},"id":"hv19630778"},
{"type":"Feature","properties":{"mag":1.92,"place":"Hawaii region, Hawaii","time":-200365056060,"updated":1585675022350,"tz":null,"url":"https://earthquake.usgs.gov/earthquakes/eventpage/hv19630777","detail":"https://earthquake.usgs.gov/fdsnws/event/1/query?eventid=hv19630777&format=geojson","felt":null,"cdi":null,"mmi":null,"alert":null,"status":"reviewed","tsunami":0,"sig":57,"net":"hv","code":"19630777","ids":",hv19630777,","sources":",hv,","types":",origin,phase-data,","nst":6,"dmin":null,"rms":0.05,"gap":166,"magType":"ml","type":"earthquake","title":"M 1.9 - Hawaii region, Hawaii"},"geometry":{"type":"Point","coordinates":[-155.3785,19.3685,7.997]},"id":"hv19630777"},
{"type":"Feature","properties":{"mag":2.25,"place":"10km ENE of Coso Junction, CA","time":-200366041290,"updated":1454011041850,"tz":null,"url":"https://earthquake.usgs.gov/earthquakes/eventpage/ci3331202","detail":"https://earthquake.usgs.gov/fdsnws/event/1/query?eventid=ci3331202&format=geojson","felt":null,"cdi":null,"mmi":null,"alert":null,"status":"reviewed","tsunami":0,"sig":78,"net":"ci","code":"3331202","ids":",ci3331202,","sources":",ci,","types":",origin,phase-data,","nst":5,"dmin":0.09149,"rms":0.38,"gap":149,"magType":"ml","type":"earthquake","title":"M 2.3 - 10km ENE of Coso Junction, CA"},"geometry":{"type":"Point","coordinates":[-117.8515,36.0883333,0]},"id":"ci3331202"},
{"type":"Feature","properties":{"mag":2.15,"place":"17km NNE of Pahala, Hawaii","time":-200371108290,"updated":1585675022210,"tz":-600,"url":"https://earthquake.usgs.gov/earthquakes/eventpage/hv19630776","detail":"https://earthquake.usgs.gov/fdsnws/event/1/query?eventid=hv19630776&format=geojson","felt":null,"cdi":null,"mmi":null,"alert":null,"status":"reviewed","tsunami":0,"sig":71,"net":"hv","code":"19630776","ids":",hv19630776,","sources":",hv,","types":",geoserve,origin,phase-data,","nst":6,"dmin":null,"rms":0.09,"gap":251,"magType":"ml","type":"earthquake","title":"M 2.2 - 17km NNE of Pahala, Hawaii"},"geometry":{"type":"Point","coordinates":[-155.4166667,19.3505,9.608]},"id":"hv19630776"},
{"type":"Feature","properties":{"mag":2,"place":"17km NNE of Pahala, Hawaii","time":-200371135380,"updated":1585675022070,"tz":-600,"url":"https://earthquake.usgs.gov/earthquakes/eventpage/hv19630775","detail":"https://earthquake.usgs.gov/fdsnws/event/1/query?eventid=hv19630775&format=geojson","felt":null,"cdi":null,"mmi":null,"alert":null,"status":"reviewed","tsunami":0,"sig":62,"net":"hv","code":"19630775","ids":",hv19630775,","sources":",hv,","types":",geoserve,origin,phase-data,","nst":6,"dmin":null,"rms":0.04,"gap":250,"magType":"ml","type":"earthquake","title":"M 2.0 - 17km NNE of Pahala, Hawaii"},"geometry":{"type":"Point","coordinates":[-155.4173333,19.3515,8.648]},"id":"hv19630775"},
{"type":"Feature","properties":{"mag":2.63,"place":"Hawaii region, Hawaii","time":-200373101830,"updated":1585675021930,"tz":null,"url":"https://earthquake.usgs.gov/earthquakes/eventpage/hv19630774","detail":"https://earthquake.usgs.gov/fdsnws/event/1/query?eventid=hv19630774&format=geojson","felt":null,"cdi":null,"mmi":null,"alert":null,"status":"reviewed","tsunami":0,"sig":106,"net":"hv","code":"19630774","ids":",hv19630774,","sources":",hv,","types":",origin,phase-data,","nst":6,"dmin":null,"rms":0.08,"gap":145,"magType":"ml","type":"earthquake","title":"M 2.6 - Hawaii region, Hawaii"},"geometry":{"type":"Point","coordinates":[-155.3781667,19.382,-0.611]},"id":"hv19630774"},
{"type":"Feature","properties":{"mag":2.13,"place":"Hawaii region, Hawaii","time":-200374507360,"updated":1585675021800,"tz":null,"url":"https://earthquake.usgs.gov/earthquakes/eventpage/hv19630773","detail":"https://earthquake.usgs.gov/fdsnws/event/1/query?eventid=hv19630773&format=geojson","felt":null,"cdi":null,"mmi":null,"alert":null,"status":"reviewed","tsunami":0,"sig":70,"net":"hv","code":"19630773","ids":",hv19630773,","sources":",hv,","types":",origin,phase-data,","nst":4,"dmin":null,"rms":0.08,"gap":285,"magType":"ml","type":"earthquake","title":"M 2.1 - Hawaii region, Hawaii"},"geometry":{"type":"Point","coordinates":[-155.4038333,19.3516667,5.741]},"id":"hv19630773"},
{"type":"Feature","properties":{"mag":1.98,"place":"Hawaii region, Hawaii","time":-200376047790,"updated":1585675021650,"tz":null,"url":"https://earthquake.usgs.gov/earthquakes/eventpage/hv19630772","detail":"https://earthquake.usgs.gov/fdsnws/event/1/query?eventid=hv19630772&format=geojson","felt":null,"cdi":null,"mmi":null,"alert":null,"status":"reviewed","tsunami":0,"sig":60,"net":"hv","code":"19630772","ids":",hv19630772,","sources":",hv,","types":",origin,phase-data,","nst":6,"dmin":null,"rms":0.05,"gap":222,"magType":"ml","type":"earthquake","title":"M 2.0 - Hawaii region, Hawaii"},"geometry":{"type":"Point","coordinates":[-155.4018333,19.3548333,8.667]},"id":"hv19630772"},
{"type":"Feature","properties":{"mag":1.87,"place":"15km WSW of Volcano, Hawaii","time":-200376325980,"updated":1585675021520,"tz":-600,"url":"https://earthquake.usgs.gov/earthquakes/eventpage/hv19630771","detail":"https://earthquake.usgs.gov/fdsnws/event/1/query?eventid=hv19630771&format=geojson","felt":null,"cdi":null,"mmi":null,"alert":null,"status":"reviewed","tsunami":0,"sig":54,"net":"hv","code":"19630771","ids":",hv19630771,","sources":",hv,","types":",geoserve,origin,phase-data,","nst":6,"dmin":null,"rms":0.12,"gap":158,"magType":"ml","type":"earthquake","title":"M 1.9 - 15km WSW of Volcano, Hawaii"},"geometry":{"type":"Point","coordinates":[-155.3735,19.3736667,6.927]},"id":"hv19630771"},
{"type":"Feature","properties":{"mag":3.11,"place":"17km NNE of Pahala, Hawaii","time":-200376696200,"updated":1585675021380,"tz":-600,"url":"https://earthquake.usgs.gov/earthquakes/eventpage/hv19630770","detail":"https://earthquake.usgs.gov/fdsnws/event/1/query?eventid=hv19630770&format=geojson","felt":null,"cdi":null,"mmi":null,"alert":null,"status":"reviewed","tsunami":0,"sig":149,"net":"hv","code":"19630770","ids":",hv19630770,","sources":",hv,","types":",geoserve,origin,phase-data,","nst":9,"dmin":null,"rms":0.16,"gap":208,"magType":"ml","type":"earthquake","title":"M 3.1 - 17km NNE of Pahala, Hawaii"},"geometry":{"type":"Point","coordinates":[-155.411,19.3535,6.137]},"id":"hv19630770"},
{"type":"Feature","properties":{"mag":2.1,"place":"Hawaii region, Hawaii","time":-200377816690,"updated":1585675021230,"tz":null,"url":"https://earthquake.usgs.gov/earthquakes/eventpage/hv19630769","detail":"https://earthquake.usgs.gov/fdsnws/event/1/query?eventid=hv19630769&format=geojson","felt":null,"cdi":null,"mmi":null,"alert":null,"status":"reviewed","tsunami":0,"sig":68,"net":"hv","code":"19630769","ids":",hv19630769,","sources":",hv,","types":",origin,phase-data,","nst":6,"dmin":null,"rms":0.08,"gap":244,"magType":"ml","type":"earthquake","title":"M 2.1 - Hawaii region, Hawaii"},"geometry":{"type":"Point","coordinates":[-155.4048333,19.345,11.697]},"id":"hv19630769"},
{"type":"Feature","properties":{"mag":2.21,"place":"Hawaii region, Hawaii","time":-200378534700,"updated":1585675021080,"tz":null,"url":"https://earthquake.usgs.gov/earthquakes/eventpage/hv19630768","detail":"https://earthquake.usgs.gov/fdsnws/event/1/query?eventid=hv19630768&format=geojson","felt":null,"cdi":null,"mmi":null,"alert":null,"status":"reviewed","tsunami":0,"sig":75,"net":"hv","code":"19630768","ids":",hv19630768,","sources":",hv,","types":",origin,phase-data,","nst":6,"dmin":null,"rms":0.14,"gap":243,"magType":"ml","type":"earthquake","title":"M 2.2 - Hawaii region, Hawaii"},"geometry":{"type":"Point","coordinates":[-155.4116667,19.3516667,11.427]},"id":"hv19630768"},
{"type":"Feature","properties":{"mag":2.04,"place":"18km WSW of Volcano, Hawaii","time":-200378811980,"updated":1585675020930,"tz":-600,"url":"https://earthquake.usgs.gov/earthquakes/eventpage/hv19630767","detail":"https://earthquake.usgs.gov/fdsnws/event/1/query?eventid=hv19630767&format=geojson","felt":null,"cdi":null,"mmi":null,"alert":null,"status":"reviewed","tsunami":0,"sig":64,"net":"hv","code":"19630767","ids":",hv19630767,","sources":",hv,","types":",geoserve,origin,phase-data,","nst":7,"dmin":null,"rms":0.06,"gap":158,"magType":"ml","type":"earthquake","title":"M 2.0 - 18km WSW of Volcano, Hawaii"},"geometry":{"type":"Point","coordinates":[-155.402,19.3771667,0.308]},"id":"hv19630767"},
{"type":"Feature","properties":{"mag":4.74,"place":"Hawaii region, Hawaii","time":-200380242230,"updated":1585675020790,"tz":null,"url":"https://earthquake.usgs.gov/earthquakes/eventpage/hv19630766","detail":"https://earthquake.usgs.gov/fdsnws/event/1/query?eventid=hv19630766&format=geojson","felt":null,"cdi":null,"mmi":null,"alert":null,"status":"reviewed","tsunami":0,"sig":346,"net":"hv","code":"19630766","ids":",ushis2619,hv19630766,","sources":",ushis,hv,","types":",impact-text,origin,phase-data,","nst":12,"dmin":null,"rms":0.05,"gap":162,"magType":"ml","type":"earthquake","title":"M 4.7 - Hawaii region, Hawaii"},"geometry":{"type":"Point","coordinates":[-155.4171667,19.35,10.398]},"id":"hv19630766"},
{"type":"Feature","properties":{"mag":2.67,"place":"4km S of Volcano, Hawaii","time":-200413455190,"updated":1585675020630,"tz":-600,"url":"https://earthquake.usgs.gov/earthquakes/eventpage/hv19630765","detail":"https://earthquake.usgs.gov/fdsnws/event/1/query?eventid=hv19630765&format=geojson","felt":null,"cdi":null,"mmi":null,"alert":null,"status":"reviewed","tsunami":0,"sig":110,"net":"hv","code":"19630765","ids":",hv19630765,","sources":",hv,","types":",geoserve,origin,phase-data,","nst":10,"dmin":null,"rms":0.07,"gap":111,"magType":"ml","type":"earthquake","title":"M 2.7 - 4km S of Volcano, Hawaii"},"geometry":{"type":"Point","coordinates":[-155.2371667,19.3928333,29.023]},"id":"hv19630765"},
{"type":"Feature","properties":{"mag":3.31,"place":"Maui region, Hawaii","time":-200416696650,"updated":1585675020490,"tz":null,"url":"https://earthquake.usgs.gov/earthquakes/eventpage/hv19630764","detail":"https://earthquake.usgs.gov/fdsnws/event/1/query?eventid=hv19630764&format=geojson","felt":null,"cdi":null,"mmi":null,"alert":null,"status":"reviewed","tsunami":0,"sig":169,"net":"hv","code":"19630764","ids":",hv19630764,","sources":",hv,","types":",origin,phase-data,","nst":6,"dmin":null,"rms":0.1,"gap":240,"magType":"ml","type":"earthquake","title":"M 3.3 - Maui region, Hawaii"},"geometry":{"type":"Point","coordinates":[-156.5398333,21.3673333,19.89]},"id":"hv19630764"},
{"type":"Feature","properties":{"mag":2.11,"place":"Hawaii region, Hawaii","time":-200473493450,"updated":1585675020350,"tz":null,"url":"https://earthquake.usgs.gov/earthquakes/eventpage/hv19630763","detail":"https://earthquake.usgs.gov/fdsnws/event/1/query?eventid=hv19630763&format=geojson","felt":null,"cdi":null,"mmi":null,"alert":null,"status":"reviewed","tsunami":0,"sig":68,"net":"hv","code":"19630763","ids":",hv19630763,","sources":",hv,","types":",origin,phase-data,","nst":6,"dmin":null,"rms":0.07,"gap":213,"magType":"ml","type":"earthquake","title":"M 2.1 - Hawaii region, Hawaii"},"geometry":{"type":"Point","coordinates":[-155.5993333,19.9836667,7.528]},"id":"hv19630763"},
{"type":"Feature","properties":{"mag":7,"place":"Fiji region","time":-200490106000,"updated":1594351290464,"tz":null,"url":"https://earthquake.usgs.gov/earthquakes/eventpage/iscgem872971","detail":"https://earthquake.usgs.gov/fdsnws/event/1/query?eventid=iscgem872971&format=geojson","felt":null,"cdi":null,"mmi":3.135,"alert":null,"status":"automatic","tsunami":0,"sig":754,"net":"iscgem","code":"872971","ids":",iscgem872971,","sources":",iscgem,","types":",origin,shakemap,","nst":null,"dmin":null,"rms":null,"gap":null,"magType":"mw","type":"earthquake","title":"M 7.0 - Fiji region"},"geometry":{"type":"Point","coordinates":[-178.684,-17.628,570]},"id":"iscgem872971"},
{"type":"Feature","properties":{"mag":3.07,"place":"Hawaii region, Hawaii","time":-200497977630,"updated":1585675020190,"tz":null,"url":"https://earthquake.usgs.gov/earthquakes/eventpage/hv19630762","detail":"https://earthquake.usgs.gov/fdsnws/event/1/query?eventid=hv19630762&format=geojson","felt":null,"cdi":null,"mmi":null,"alert":null,"status":"reviewed","tsunami":0,"sig":145,"net":"hv","code":"19630762","ids":",hv19630762,","sources":",hv,","types":",origin,phase-data,","nst":9,"dmin":null,"rms":0.04,"gap":346,"magType":"ml","type":"earthquake","title":"M 3.1 - Hawaii region, Hawaii"},"geometry":{"type":"Point","coordinates":[-155.3076667,18.9921667,5.696]},"id":"hv19630762"},
{"type":"Feature","properties":{"mag":5.3,"place":"eastern Turkey","time":-200512094000,"updated":1436806943000,"tz":null,"url":"https://earthquake.usgs.gov/earthquakes/eventpage/iscgemsup872970","detail":"https://earthquake.usgs.gov/fdsnws/event/1/query?eventid=iscgemsup872970&format=geojson","felt":null,"cdi":null,"mmi":null,"alert":null,"status":"automatic","tsunami":0,"sig":432,"net":"iscgemsup","code":"872970","ids":",iscgemsup872970,","sources":",iscgemsup,","types":",origin,","nst":null,"dmin":null,"rms":null,"gap":null,"magType":"mw","type":"earthquake","title":"M 5.3 - eastern Turkey"},"geometry":{"type":"Point","coordinates":[38.477,39.019,35]},"id":"iscgemsup872970"},
{"type":"Feature","properties":{"mag":2.77,"place":"4km NE of Stanton, CA","time":-200512325690,"updated":1454009747800,"tz":null,"url":"https://earthquake.usgs.gov/earthquakes/eventpage/ci3331201","detail":"https://earthquake.usgs.gov/fdsnws/event/1/query?eventid=ci3331201&format=geojson","felt":null,"cdi":null,"mmi":null,"alert":null,"status":"reviewed","tsunami":0,"sig":118,"net":"ci","code":"3331201","ids":",ci3331201,","sources":",ci,","types":",origin,phase-data,","nst":7,"dmin":0.3613,"rms":0.43,"gap":208,"magType":"ml","type":"earthquake","title":"M 2.8 - 4km NE of Stanton, CA"},"geometry":{"type":"Point","coordinates":[-117.967,33.8286667,6]},"id":"ci3331201"},
{"type":"Feature","properties":{"mag":2.43,"place":"3km S of Granada Hills, CA","time":-200513342900,"updated":1454010527980,"tz":null,"url":"https://earthquake.usgs.gov/earthquakes/eventpage/ci3331200","detail":"https://earthquake.usgs.gov/fdsnws/event/1/query?eventid=ci3331200&format=geojson","felt":null,"cdi":null,"mmi":null,"alert":null,"status":"reviewed","tsunami":0,"sig":91,"net":"ci","code":"3331200","ids":",ci3331200,","sources":",ci,","types":",origin,phase-data,","nst":9,"dmin":0.2888,"rms":0.49,"gap":197,"magType":"ml","type":"earthquake","title":"M 2.4 - 3km S of Granada Hills, CA"},"geometry":{"type":"Point","coordinates":[-118.498,34.2488333,3.94]},"id":"ci3331200"},
{"type":"Feature","properties":{"mag":4.08,"place":"36km E of Ensenada, B.C., MX","time":-200545935970,"updated":1454011294390,"tz":null,"url":"https://earthquake.usgs.gov/earthquakes/eventpage/ci3331230","detail":"https://earthquake.usgs.gov/fdsnws/event/1/query?eventid=ci3331230&format=geojson","felt":null,"cdi":null,"mmi":null,"alert":null,"status":"reviewed","tsunami":0,"sig":256,"net":"ci","code":"3331230","ids":",ci3331230,","sources":",ci,","types":",origin,phase-data,","nst":7,"dmin":0.8514,"rms":0.37,"gap":310,"magType":"ml","type":"earthquake","title":"M 4.1 - 36km E of Ensenada, B.C., MX"},"geometry":{"type":"Point","coordinates":[-116.2431667,31.9078333,6]},"id":"ci3331230"},
{"type":"Feature","properties":{"mag":3.14,"place":"29km ENE of Coso Junction, CA","time":-200548945500,"updated":1454009495600,"tz":null,"url":"https://earthquake.usgs.gov/earthquakes/eventpage/ci3331198","detail":"https://earthquake.usgs.gov/fdsnws/event/1/query?eventid=ci3331198&format=geojson","felt":null,"cdi":null,"mmi":null,"alert":null,"status":"reviewed","tsunami":0,"sig":152,"net":"ci","code":"3331198","ids":",ci3331198,","sources":",ci,","types":",origin,phase-data,","nst":8,"dmin":0.2273,"rms":0.47,"gap":167,"magType":"ml","type":"earthquake","title":"M 3.1 - 29km ENE of Coso Junction, CA"},"geometry":{"type":"Point","coordinates":[-117.6713333,36.1781667,10.56]},"id":"ci3331198"},
{"type":"Feature","properties":{"mag":2.98,"place":"10km WSW of Twentynine Palms, CA","time":-200572299250,"updated":1454010527460,"tz":null,"url":"https://earthquake.usgs.gov/earthquakes/eventpage/ci3331197","detail":"https://earthquake.usgs.gov/fdsnws/event/1/query?eventid=ci3331197&format=geojson","felt":null,"cdi":null,"mmi":null,"alert":null,"status":"reviewed","tsunami":0,"sig":137,"net":"ci","code":"3331197","ids":",ci3331197,","sources":",ci,","types":",origin,phase-data,","nst":7,"dmin":0.5825,"rms":0.48,"gap":154,"magType":"ml","type":"earthquake","title":"M 3.0 - 10km WSW of Twentynine Palms, CA"},"geometry":{"type":"Point","coordinates":[-116.1626667,34.095,6]},"id":"ci3331197"},
{"type":"Feature","properties":{"mag":3.11,"place":"3km W of Kailua-Kona, Hawaii","time":-200573859220,"updated":1585675020050,"tz":-600,"url":"https://earthquake.usgs.gov/earthquakes/eventpage/hv19630761","detail":"https://earthquake.usgs.gov/fdsnws/event/1/query?eventid=hv19630761&format=geojson","felt":null,"cdi":null,"mmi":null,"alert":null,"status":"reviewed","tsunami":0,"sig":149,"net":"hv","code":"19630761","ids":",hv19630761,","sources":",hv,","types":",geoserve,origin,phase-data,","nst":7,"dmin":null,"rms":0.13,"gap":320,"magType":"ml","type":"earthquake","title":"M 3.1 - 3km W of Kailua-Kona, Hawaii"},"geometry":{"type":"Point","coordinates":[-156.033,19.6365,5.928]},"id":"hv19630761"},
{"type":"Feature","properties":{"mag":3.64,"place":"25km ENE of Coso Junction, CA","time":-200581853460,"updated":1454011041320,"tz":null,"url":"https://earthquake.usgs.gov/earthquakes/eventpage/ci3331194","detail":"https://earthquake.usgs.gov/fdsnws/event/1/query?eventid=ci3331194&format=geojson","felt":null,"cdi":null,"mmi":null,"alert":null,"status":"reviewed","tsunami":0,"sig":204,"net":"ci","code":"3331194","ids":",ci3331194,","sources":",ci,","types":",origin,phase-data,","nst":11,"dmin":0.2165,"rms":0.29,"gap":163,"magType":"ml","type":"earthquake","title":"M 3.6 - 25km ENE of Coso Junction, CA"},"geometry":{"type":"Point","coordinates":[-117.6811667,36.1171667,0.85]},"id":"ci3331194"},
{"type":"Feature","properties":{"mag":2.45,"place":"2km NE of Stanton, CA","time":-200636567830,"updated":1454011040820,"tz":null,"url":"https://earthquake.usgs.gov/earthquakes/eventpage/ci3331193","detail":"https://earthquake.usgs.gov/fdsnws/event/1/query?eventid=ci3331193&format=geojson","felt":null,"cdi":null,"mmi":null,"alert":null,"status":"reviewed","tsunami":0,"sig":92,"net":"ci","code":"3331193","ids":",ci3331193,","sources":",ci,","types":",origin,phase-data,","nst":8,"dmin":0.3665,"rms":0.36,"gap":190,"magType":"ml","type":"earthquake","title":"M 2.5 - 2km NE of Stanton, CA"},"geometry":{"type":"Point","coordinates":[-117.975,33.8193333,4.68]},"id":"ci3331193"},
{"type":"Feature","properties":{"mag":2.4,"place":"Hawaii region, Hawaii","time":-200655765280,"updated":1585675019910,"tz":null,"url":"https://earthquake.usgs.gov/earthquakes/eventpage/hv19630760","detail":"https://earthquake.usgs.gov/fdsnws/event/1/query?eventid=hv19630760&format=geojson","felt":null,"cdi":null,"mmi":null,"alert":null,"status":"reviewed","tsunami":0,"sig":89,"net":"hv","code":"19630760","ids":",hv19630760,","sources":",hv,","types":",origin,phase-data,","nst":5,"dmin":null,"rms":0.15,"gap":327,"magType":"ml","type":"earthquake","title":"M 2.4 - Hawaii region, Hawaii"},"geometry":{"type":"Point","coordinates":[-154.75,19.3945,9.009]},"id":"hv19630760"},
{"type":"Feature","properties":{"mag":3.77,"place":"68km ENE of Beatty, NV","time":-200659198690,"updated":1454009493580,"tz":null,"url":"https://earthquake.usgs.gov/earthquakes/eventpage/ci3332185","detail":"https://earthquake.usgs.gov/fdsnws/event/1/query?eventid=ci3332185&format=geojson","felt":null,"cdi":null,"mmi":null,"alert":null,"status":"reviewed","tsunami":0,"sig":219,"net":"ci","code":"3332185","ids":",ci3332185,","sources":",ci,","types":",origin,phase-data,","nst":12,"dmin":1.756,"rms":0.5,"gap":265,"magType":"ml","type":"nuclear explosion","title":"M 3.8 Nuclear Explosion - 68km ENE of Beatty, NV"},"geometry":{"type":"Point","coordinates":[-116.0353333,37.125,0.3]},"id":"ci3332185"},
{"type":"Feature","properties":{"mag":5.6,"place":"off the east coast of the Kamchatka Peninsula, Russia","time":-200659833000,"updated":1431543177000,"tz":null,"url":"https://earthquake.usgs.gov/earthquakes/eventpage/iscgem872964","detail":"https://earthquake.usgs.gov/fdsnws/event/1/query?eventid=iscgem872964&format=geojson","felt":null,"cdi":null,"mmi":null,"alert":null,"status":"automatic","tsunami":0,"sig":482,"net":"iscgem","code":"872964","ids":",iscgem872964,","sources":",iscgem,","types":",origin,","nst":null,"dmin":null,"rms":null,"gap":null,"magType":"mw","type":"earthquake","title":"M 5.6 - off the east coast of the Kamchatka Peninsula, Russia"},"geometry":{"type":"Point","coordinates":[159.496,52.295,35]},"id":"iscgem872964"},
{"type":"Feature","properties":{"mag":6.3,"place":"Solomon Islands","time":-200722056000,"updated":1431543177000,"tz":null,"url":"https://earthquake.usgs.gov/earthquakes/eventpage/iscgem872961","detail":"https://earthquake.usgs.gov/fdsnws/event/1/query?eventid=iscgem872961&format=geojson","felt":null,"cdi":null,"mmi":null,"alert":null,"status":"automatic","tsunami":0,"sig":611,"net":"iscgem","code":"872961","ids":",iscgem872961,","sources":",iscgem,","types":",origin,","nst":null,"dmin":null,"rms":null,"gap":null,"magType":"mw","type":"earthquake","title":"M 6.3 - Solomon Islands"},"geometry":{"type":"Point","coordinates":[158.403,-9.473,15]},"id":"iscgem872961"},
{"type":"Feature","properties":{"mag":1.99,"place":"2km NNE of Garden Grove, CA","time":-200748700650,"updated":1454009495130,"tz":null,"url":"https://earthquake.usgs.gov/earthquakes/eventpage/ci3331192","detail":"https://earthquake.usgs.gov/fdsnws/event/1/query?eventid=ci3331192&format=geojson","felt":null,"cdi":null,"mmi":null,"alert":null,"status":"reviewed","tsunami":0,"sig":61,"net":"ci","code":"3331192","ids":",ci3331192,","sources":",ci,","types":",origin,phase-data,","nst":5,"dmin":0.3972,"rms":0.29,"gap":198,"magType":"ml","type":"earthquake","title":"M 2.0 - 2km NNE of Garden Grove, CA"},"geometry":{"type":"Point","coordinates":[-117.9525,33.7943333,6]},"id":"ci3331192"},
{"type":"Feature","properties":{"mag":2.24,"place":"2km W of Garden Grove, CA","time":-200749012510,"updated":1454009747310,"tz":null,"url":"https://earthquake.usgs.gov/earthquakes/eventpage/ci3331191","detail":"https://earthquake.usgs.gov/fdsnws/event/1/query?eventid=ci3331191&format=geojson","felt":null,"cdi":null,"mmi":null,"alert":null,"status":"reviewed","tsunami":0,"sig":77,"net":"ci","code":"3331191","ids":",ci3331191,","sources":",ci,","types":",origin,phase-data,","nst":6,"dmin":0.3973,"rms":0.43,"gap":204,"magType":"ml","type":"earthquake","title":"M 2.2 - 2km W of Garden Grove, CA"},"geometry":{"type":"Point","coordinates":[-117.9858333,33.7813333,6]},"id":"ci3331191"},
{"type":"Feature","properties":{"mag":3.72,"place":"0km WSW of Westminster, CA","time":-200749608440,"updated":1454011040250,"tz":null,"url":"https://earthquake.usgs.gov/earthquakes/eventpage/ci3331189","detail":"https://earthquake.usgs.gov/fdsnws/event/1/query?eventid=ci3331189&format=geojson","felt":null,"cdi":null,"mmi":null,"alert":null,"status":"reviewed","tsunami":0,"sig":213,"net":"ci","code":"3331189","ids":",ci3331189,","sources":",ci,","types":",origin,phase-data,","nst":10,"dmin":0.411,"rms":0.47,"gap":116,"magType":"ml","type":"earthquake","title":"M 3.7 - 0km WSW of Westminster, CA"},"geometry":{"type":"Point","coordinates":[-118.0125,33.7581667,6]},"id":"ci3331189"},
{"type":"Feature","properties":{"mag":2.72,"place":"11km W of Twentynine Palms, CA","time":-200773637300,"updated":1454010526970,"tz":null,"url":"https://earthquake.usgs.gov/earthquakes/eventpage/ci3331261","detail":"https://earthquake.usgs.gov/fdsnws/event/1/query?eventid=ci3331261&format=geojson","felt":null,"cdi":null,"mmi":null,"alert":null,"status":"reviewed","tsunami":0,"sig":114,"net":"ci","code":"3331261","ids":",ci3331261,","sources":",ci,","types":",origin,phase-data,","nst":7,"dmin":0.6378,"rms":0.36,"gap":156,"magType":"mh","type":"earthquake","title":"M 2.7 - 11km W of Twentynine Palms, CA"},"geometry":{"type":"Point","coordinates":[-116.1898333,34.1523333,6]},"id":"ci3331261"},
{"type":"Feature","properties":{"mag":2.94,"place":"11km ENE of Joshua Tree, CA","time":-200776236470,"updated":1454011293860,"tz":null,"url":"https://earthquake.usgs.gov/earthquakes/eventpage/ci3331260","detail":"https://earthquake.usgs.gov/fdsnws/event/1/query?eventid=ci3331260&format=geojson","felt":null,"cdi":null,"mmi":null,"alert":null,"status":"reviewed","tsunami":0,"sig":133,"net":"ci","code":"3331260","ids":",ci3331260,","sources":",ci,","types":",origin,phase-data,","nst":7,"dmin":0.6462,"rms":0.35,"gap":156,"magType":"ml","type":"earthquake","title":"M 2.9 - 11km ENE of Joshua Tree, CA"},"geometry":{"type":"Point","coordinates":[-116.1991667,34.1563333,6]},"id":"ci3331260"},
{"type":"Feature","properties":{"mag":4.15,"place":"11km W of Twentynine Palms, CA","time":-200777163810,"updated":1454010267290,"tz":null,"url":"https://earthquake.usgs.gov/earthquakes/eventpage/ci3331259","detail":"https://earthquake.usgs.gov/fdsnws/event/1/query?eventid=ci3331259&format=geojson","felt":null,"cdi":null,"mmi":null,"alert":null,"status":"reviewed","tsunami":0,"sig":265,"net":"ci","code":"3331259","ids":",ci3331259,","sources":",ci,","types":",origin,phase-data,","nst":13,"dmin":0.634,"rms":0.53,"gap":156,"magType":"ml","type":"earthquake","title":"M 4.2 - 11km W of Twentynine Palms, CA"},"geometry":{"type":"Point","coordinates":[-116.192,34.1448333,6]},"id":"ci3331259"},
{"type":"Feature","properties":{"mag":2.24,"place":"Hawaii region, Hawaii","time":-200793683660,"updated":1585675019770,"tz":null,"url":"https://earthquake.usgs.gov/earthquakes/eventpage/hv19630759","detail":"https://earthquake.usgs.gov/fdsnws/event/1/query?eventid=hv19630759&format=geojson","felt":null,"cdi":null,"mmi":null,"alert":null,"status":"reviewed","tsunami":0,"sig":77,"net":"hv","code":"19630759","ids":",hv19630759,","sources":",hv,","types":",origin,phase-data,","nst":6,"dmin":null,"rms":0.07,"gap":245,"magType":"ml","type":"earthquake","title":"M 2.2 - Hawaii region, Hawaii"},"geometry":{"type":"Point","coordinates":[-155.1926667,19.364,-0.982]},"id":"hv19630759"},
{"type":"Feature","properties":{"mag":2.37,"place":"11km SE of Volcano, Hawaii","time":-200794191800,"updated":1585675019620,"tz":-600,"url":"https://earthquake.usgs.gov/earthquakes/eventpage/hv19630758","detail":"https://earthquake.usgs.gov/fdsnws/event/1/query?eventid=hv19630758&format=geojson","felt":null,"cdi":null,"mmi":null,"alert":null,"status":"reviewed","tsunami":0,"sig":86,"net":"hv","code":"19630758","ids":",hv19630758,","sources":",hv,","types":",geoserve,origin,phase-data,","nst":6,"dmin":null,"rms":0.1,"gap":255,"magType":"ml","type":"earthquake","title":"M 2.4 - 11km SE of Volcano, Hawaii"},"geometry":{"type":"Point","coordinates":[-155.1601667,19.3528333,2.954]},"id":"hv19630758"},
{"type":"Feature","properties":{"mag":2.06,"place":"Hawaii region, Hawaii","time":-200794267460,"updated":1585675019490,"tz":null,"url":"https://earthquake.usgs.gov/earthquakes/eventpage/hv19630757","detail":"https://earthquake.usgs.gov/fdsnws/event/1/query?eventid=hv19630757&format=geojson","felt":null,"cdi":null,"mmi":null,"alert":null,"status":"reviewed","tsunami":0,"sig":65,"net":"hv","code":"19630757","ids":",hv19630757,","sources":",hv,","types":",origin,phase-data,","nst":4,"dmin":null,"rms":0.04,"gap":248,"magType":"ml","type":"earthquake","title":"M 2.1 - Hawaii region, Hawaii"},"geometry":{"type":"Point","coordinates":[-155.186,19.361,3.178]},"id":"hv19630757"},
{"type":"Feature","properties":{"mag":2.72,"place":"12km S of Maricopa, CA","time":-200818693180,"updated":1454011293380,"tz":null,"url":"https://earthquake.usgs.gov/earthquakes/eventpage/ci3331258","detail":"https://earthquake.usgs.gov/fdsnws/event/1/query?eventid=ci3331258&format=geojson","felt":null,"cdi":null,"mmi":null,"alert":null,"status":"reviewed","tsunami":0,"sig":114,"net":"ci","code":"3331258","ids":",ci3331258,","sources":",ci,","types":",origin,phase-data,","nst":8,"dmin":0.4245,"rms":0.42,"gap":184,"magType":"ml","type":"earthquake","title":"M 2.7 - 12km S of Maricopa, CA"},"geometry":{"type":"Point","coordinates":[-119.4075,34.9516667,6]},"id":"ci3331258"},
{"type":"Feature","properties":{"mag":5.7,"place":"Hokkaido, Japan region","time":-200909508000,"updated":1431543177000,"tz":null,"url":"https://earthquake.usgs.gov/earthquakes/eventpage/iscgem872954","detail":"https://earthquake.usgs.gov/fdsnws/event/1/query?eventid=iscgem872954&format=geojson","felt":null,"cdi":null,"mmi":null,"alert":null,"status":"automatic","tsunami":0,"sig":500,"net":"iscgem","code":"872954","ids":",iscgem872954,","sources":",iscgem,","types":",origin,","nst":null,"dmin":null,"rms":null,"gap":null,"magType":"mw","type":"earthquake","title":"M 5.7 - Hokkaido, Japan region"},"geometry":{"type":"Point","coordinates":[142.967,41.212,42.8]},"id":"iscgem872954"},
{"type":"Feature","properties":{"mag":2.72,"place":"5km SSW of Volcano, Hawaii","time":-201009419850,"updated":1585675019340,"tz":-600,"url":"https://earthquake.usgs.gov/earthquakes/eventpage/hv19630756","detail":"https://earthquake.usgs.gov/fdsnws/event/1/query?eventid=hv19630756&format=geojson","felt":null,"cdi":null,"mmi":null,"alert":null,"status":"reviewed","tsunami":0,"sig":114,"net":"hv","code":"19630756","ids":",hv19630756,","sources":",hv,","types":",geoserve,origin,phase-data,","nst":10,"dmin":null,"rms":0.08,"gap":94,"magType":"ml","type":"earthquake","title":"M 2.7 - 5km SSW of Volcano, Hawaii"},"geometry":{"type":"Point","coordinates":[-155.2586667,19.3851667,30.593]},"id":"hv19630756"},
{"type":"Feature","properties":{"mag":2.45,"place":"Hawaii region, Hawaii","time":-201043160180,"updated":1585675019190,"tz":null,"url":"https://earthquake.usgs.gov/earthquakes/eventpage/hv19630755","detail":"https://earthquake.usgs.gov/fdsnws/event/1/query?eventid=hv19630755&format=geojson","felt":null,"cdi":null,"mmi":null,"alert":null,"status":"reviewed","tsunami":0,"sig":92,"net":"hv","code":"19630755","ids":",hv19630755,","sources":",hv,","types":",origin,phase-data,","nst":9,"dmin":null,"rms":0.06,"gap":222,"magType":"ml","type":"earthquake","title":"M 2.5 - Hawaii region, Hawaii"},"geometry":{"type":"Point","coordinates":[-155.1633333,19.3246667,6.203]},"id":"hv19630755"},
{"type":"Feature","properties":{"mag":5.6,"place":"south of the Kermadec Islands","time":-201065540000,"updated":1431543177000,"tz":null,"url":"https://earthquake.usgs.gov/earthquakes/eventpage/iscgem872946","detail":"https://earthquake.usgs.gov/fdsnws/event/1/query?eventid=iscgem872946&format=geojson","felt":null,"cdi":null,"mmi":null,"alert":null,"status":"automatic","tsunami":0,"sig":482,"net":"iscgem","code":"872946","ids":",iscgem872946,","sources":",iscgem,","types":",origin,","nst":null,"dmin":null,"rms":null,"gap":null,"magType":"mw","type":"earthquake","title":"M 5.6 - south of the Kermadec Islands"},"geometry":{"type":"Point","coordinates":[-177.856,-32.064,15]},"id":"iscgem872946"},
{"type":"Feature","properties":{"mag":5.6,"place":"Andreanof Islands, Aleutian Islands, Alaska","time":-201071804000,"updated":1557868932219,"tz":null,"url":"https://earthquake.usgs.gov/earthquakes/eventpage/iscgem872945","detail":"https://earthquake.usgs.gov/fdsnws/event/1/query?eventid=iscgem872945&format=geojson","felt":null,"cdi":null,"mmi":null,"alert":null,"status":"automatic","tsunami":0,"sig":482,"net":"iscgem","code":"872945","ids":",ushis2618,iscgem872945,","sources":",ushis,iscgem,","types":",impact-text,origin,trump-origin,","nst":null,"dmin":null,"rms":null,"gap":null,"magType":"mw","type":"earthquake","title":"M 5.6 - Andreanof Islands, Aleutian Islands, Alaska"},"geometry":{"type":"Point","coordinates":[-177.082,50.357,21.6]},"id":"iscgem872945"},
{"type":"Feature","properties":{"mag":2.54,"place":"4km W of Costa Mesa, CA","time":-201095621410,"updated":1454009746830,"tz":null,"url":"https://earthquake.usgs.gov/earthquakes/eventpage/ci3331257","detail":"https://earthquake.usgs.gov/fdsnws/event/1/query?eventid=ci3331257&format=geojson","felt":null,"cdi":null,"mmi":null,"alert":null,"status":"reviewed","tsunami":0,"sig":99,"net":"ci","code":"3331257","ids":",ci3331257,","sources":",ci,","types":",origin,phase-data,","nst":7,"dmin":0.5101,"rms":0.68,"gap":196,"magType":"ml","type":"earthquake","title":"M 2.5 - 4km W of Costa Mesa, CA"},"geometry":{"type":"Point","coordinates":[-117.9546667,33.67,6]},"id":"ci3331257"},
{"type":"Feature","properties":{"mag":2.73,"place":"11km WNW of Garnet, CA","time":-201113548560,"updated":1454009494630,"tz":null,"url":"https://earthquake.usgs.gov/earthquakes/eventpage/ci3331256","detail":"https://earthquake.usgs.gov/fdsnws/event/1/query?eventid=ci3331256&format=geojson","felt":null,"cdi":null,"mmi":null,"alert":null,"status":"reviewed","tsunami":0,"sig":115,"net":"ci","code":"3331256","ids":",ci3331256,","sources":",ci,","types":",origin,phase-data,","nst":7,"dmin":0.5951,"rms":0.31,"gap":108,"magType":"ml","type":"earthquake","title":"M 2.7 - 11km WNW of Garnet, CA"},"geometry":{"type":"Point","coordinates":[-116.664,33.9266667,6]},"id":"ci3331256"},
{"type":"Feature","properties":{"mag":2.44,"place":"5km SW of Volcano, Hawaii","time":-201126588200,"updated":1585675019050,"tz":-600,"url":"https://earthquake.usgs.gov/earthquakes/eventpage/hv19630754","detail":"https://earthquake.usgs.gov/fdsnws/event/1/query?eventid=hv19630754&format=geojson","felt":null,"cdi":null,"mmi":null,"alert":null,"status":"reviewed","tsunami":0,"sig":92,"net":"hv","code":"19630754","ids":",hv19630754,","sources":",hv,","types":",geoserve,origin,phase-data,","nst":7,"dmin":null,"rms":0.04,"gap":136,"magType":"ml","type":"earthquake","title":"M 2.4 - 5km SW of Volcano, Hawaii"},"geometry":{"type":"Point","coordinates":[-155.271,19.395,28.803]},"id":"hv19630754"},
{"type":"Feature","properties":{"mag":6.4,"place":"Kyushu, Japan","time":-201185236000,"updated":1594351277873,"tz":null,"url":"https://earthquake.usgs.gov/earthquakes/eventpage/iscgem872938","detail":"https://earthquake.usgs.gov/fdsnws/event/1/query?eventid=iscgem872938&format=geojson","felt":null,"cdi":null,"mmi":5.764,"alert":null,"status":"automatic","tsunami":0,"sig":630,"net":"iscgem","code":"872938","ids":",iscgem872938,","sources":",iscgem,","types":",origin,shakemap,","nst":null,"dmin":null,"rms":null,"gap":null,"magType":"mw","type":"earthquake","title":"M 6.4 - Kyushu, Japan"},"geometry":{"type":"Point","coordinates":[131.148,30.52,35]},"id":"iscgem872938"},
{"type":"Feature","properties":{"mag":3.9,"place":"19km E of King City, CA","time":-201321506040,"updated":1454010266720,"tz":null,"url":"https://earthquake.usgs.gov/earthquakes/eventpage/ci3331255","detail":"https://earthquake.usgs.gov/fdsnws/event/1/query?eventid=ci3331255&format=geojson","felt":null,"cdi":null,"mmi":null,"alert":null,"status":"reviewed","tsunami":0,"sig":234,"net":"ci","code":"3331255","ids":",ci3331255,","sources":",ci,","types":",origin,phase-data,","nst":9,"dmin":1.286,"rms":0.51,"gap":300,"magType":"ml","type":"earthquake","title":"M 3.9 - 19km E of King City, CA"},"geometry":{"type":"Point","coordinates":[-120.9123333,36.1966667,6]},"id":"ci3331255"},
{"type":"Feature","properties":{"mag":3.84,"place":"19km NE of King City, CA","time":-201322648580,"updated":1454011292810,"tz":null,"url":"https://earthquake.usgs.gov/earthquakes/eventpage/ci3331254","detail":"https://earthquake.usgs.gov/fdsnws/event/1/query?eventid=ci3331254&format=geojson","felt":null,"cdi":null,"mmi":null,"alert":null,"status":"reviewed","tsunami":0,"sig":227,"net":"ci","code":"3331254","ids":",ci3331254,","sources":",ci,","types":",origin,phase-data,","nst":7,"dmin":1.423,"rms":0.24,"gap":315,"magType":"ml","type":"earthquake","title":"M 3.8 - 19km NE of King City, CA"},"geometry":{"type":"Point","coordinates":[-120.984,36.3356667,6]},"id":"ci3331254"},
{"type":"Feature","properties":{"mag":2.55,"place":"18km SSE of Volcano, Hawaii","time":-201322723700,"updated":1585675018910,"tz":-600,"url":"https://earthquake.usgs.gov/earthquakes/eventpage/hv19630753","detail":"https://earthquake.usgs.gov/fdsnws/event/1/query?eventid=hv19630753&format=geojson","felt":null,"cdi":null,"mmi":null,"alert":null,"status":"reviewed","tsunami":0,"sig":100,"net":"hv","code":"19630753","ids":",hv19630753,","sources":",hv,","types":",geoserve,origin,phase-data,","nst":8,"dmin":null,"rms":0.11,"gap":197,"magType":"ml","type":"earthquake","title":"M 2.6 - 18km SSE of Volcano, Hawaii"},"geometry":{"type":"Point","coordinates":[-155.1683333,19.2798333,-0.033]},"id":"hv19630753"},
{"type":"Feature","properties":{"mag":3.04,"place":"10km E of Honaunau-Napoopoo, Hawaii","time":-201324497390,"updated":1585675018770,"tz":-600,"url":"https://earthquake.usgs.gov/earthquakes/eventpage/hv19630752","detail":"https://earthquake.usgs.gov/fdsnws/event/1/query?eventid=hv19630752&format=geojson","felt":null,"cdi":null,"mmi":null,"alert":null,"status":"reviewed","tsunami":0,"sig":142,"net":"hv","code":"19630752","ids":",hv19630752,","sources":",hv,","types":",geoserve,origin,phase-data,","nst":9,"dmin":null,"rms":0.17,"gap":272,"magType":"ml","type":"earthquake","title":"M 3.0 - 10km E of Honaunau-Napoopoo, Hawaii"},"geometry":{"type":"Point","coordinates":[-155.7648333,19.4743333,-1.072]},"id":"hv19630752"},
{"type":"Feature","properties":{"mag":7.7,"place":"southern Peru","time":-201335691000,"updated":1594333404802,"tz":null,"url":"https://earthquake.usgs.gov/earthquakes/eventpage/iscgem17294122","detail":"https://earthquake.usgs.gov/fdsnws/event/1/query?eventid=iscgem17294122&format=geojson","felt":null,"cdi":null,"mmi":3.783,"alert":null,"status":"automatic","tsunami":0,"sig":912,"net":"iscgem","code":"17294122","ids":",iscgem17294122,","sources":",iscgem,","types":",origin,shakemap,","nst":null,"dmin":null,"rms":null,"gap":null,"magType":"mw","type":"earthquake","title":"M 7.7 - southern Peru"},"geometry":{"type":"Point","coordinates":[-69.414,-13.866,550]},"id":"iscgem17294122"},
{"type":"Feature","properties":{"mag":3.99,"place":"66km ENE of Beatty, NV","time":-201351598790,"updated":1454011291780,"tz":null,"url":"https://earthquake.usgs.gov/earthquakes/eventpage/ci3332184","detail":"https://earthquake.usgs.gov/fdsnws/event/1/query?eventid=ci3332184&format=geojson","felt":null,"cdi":null,"mmi":null,"alert":null,"status":"reviewed","tsunami":0,"sig":245,"net":"ci","code":"3332184","ids":",ci3332184,","sources":",ci,","types":",origin,phase-data,","nst":15,"dmin":1.724,"rms":1.08,"gap":265,"magType":"ml","type":"nuclear explosion","title":"M 4.0 Nuclear Explosion - 66km ENE of Beatty, NV"},"geometry":{"type":"Point","coordinates":[-116.0766667,37.1541667,0.2]},"id":"ci3332184"},
{"type":"Feature","properties":{"mag":6.5,"place":"near the east coast of Honshu, Japan","time":-201376108000,"updated":1594351263017,"tz":null,"url":"https://earthquake.usgs.gov/earthquakes/eventpage/iscgem872929","detail":"https://earthquake.usgs.gov/fdsnws/event/1/query?eventid=iscgem872929&format=geojson","felt":null,"cdi":null,"mmi":4.495,"alert":null,"status":"automatic","tsunami":0,"sig":650,"net":"iscgem","code":"872929","ids":",iscgem872929,","sources":",iscgem,","types":",origin,shakemap,","nst":null,"dmin":null,"rms":null,"gap":null,"magType":"mw","type":"earthquake","title":"M 6.5 - near the east coast of Honshu, Japan"},"geometry":{"type":"Point","coordinates":[141.883,37.721,35]},"id":"iscgem872929"},
{"type":"Feature","properties":{"mag":5.5,"place":"Bonin Islands, Japan region","time":-201390160000,"updated":1431543177000,"tz":null,"url":"https://earthquake.usgs.gov/earthquakes/eventpage/iscgem872928","detail":"https://earthquake.usgs.gov/fdsnws/event/1/query?eventid=iscgem872928&format=geojson","felt":null,"cdi":null,"mmi":null,"alert":null,"status":"automatic","tsunami":0,"sig":465,"net":"iscgem","code":"872928","ids":",iscgem872928,","sources":",iscgem,","types":",origin,","nst":null,"dmin":null,"rms":null,"gap":null,"magType":"mw","type":"earthquake","title":"M 5.5 - Bonin Islands, Japan region"},"geometry":{"type":"Point","coordinates":[139.894,28.01,494.2]},"id":"iscgem872928"},
{"type":"Feature","properties":{"mag":5.7,"place":"Papua, Indonesia","time":-201417363000,"updated":1594351251444,"tz":null,"url":"https://earthquake.usgs.gov/earthquakes/eventpage/iscgem872926","detail":"https://earthquake.usgs.gov/fdsnws/event/1/query?eventid=iscgem872926&format=geojson","felt":null,"cdi":null,"mmi":5.293,"alert":null,"status":"automatic","tsunami":0,"sig":500,"net":"iscgem","code":"872926","ids":",iscgem872926,","sources":",iscgem,","types":",origin,shakemap,","nst":null,"dmin":null,"rms":null,"gap":null,"magType":"mw","type":"earthquake","title":"M 5.7 - Papua, Indonesia"},"geometry":{"type":"Point","coordinates":[135.53,-3.282,35]},"id":"iscgem872926"},
{"type":"Feature","properties":{"mag":2.76,"place":"10km NNE of Claremont, CA","time":-201420712030,"updated":1454009494120,"tz":null,"url":"https://earthquake.usgs.gov/earthquakes/eventpage/ci3331253","detail":"https://earthquake.usgs.gov/fdsnws/event/1/query?eventid=ci3331253&format=geojson","felt":null,"cdi":null,"mmi":null,"alert":null,"status":"reviewed","tsunami":0,"sig":117,"net":"ci","code":"3331253","ids":",ci3331253,","sources":",ci,","types":",origin,phase-data,","nst":8,"dmin":0.3105,"rms":0.6,"gap":116,"magType":"ml","type":"earthquake","title":"M 2.8 - 10km NNE of Claremont, CA"},"geometry":{"type":"Point","coordinates":[-117.6868333,34.183,0]},"id":"ci3331253"},
{"type":"Feature","properties":{"mag":4.03,"place":"Oahu region, Hawaii","time":-201429265070,"updated":1585675018610,"tz":null,"url":"https://earthquake.usgs.gov/earthquakes/eventpage/hv19630751","detail":"https://earthquake.usgs.gov/fdsnws/event/1/query?eventid=hv19630751&format=geojson","felt":null,"cdi":null,"mmi":null,"alert":null,"status":"reviewed","tsunami":0,"sig":250,"net":"hv","code":"19630751","ids":",hv19630751,","sources":",hv,","types":",origin,phase-data,","nst":6,"dmin":null,"rms":0.09,"gap":325,"magType":"ml","type":"earthquake","title":"M 4.0 - Oahu region, Hawaii"},"geometry":{"type":"Point","coordinates":[-158.3316667,21.6925,29.89]},"id":"hv19630751"},
{"type":"Feature","properties":{"mag":5.7,"place":"New Britain region, Papua New Guinea","time":-201472047000,"updated":1594351240798,"tz":null,"url":"https://earthquake.usgs.gov/earthquakes/eventpage/iscgem872922","detail":"https://earthquake.usgs.gov/fdsnws/event/1/query?eventid=iscgem872922&format=geojson","felt":null,"cdi":null,"mmi":4.199,"alert":null,"status":"automatic","tsunami":0,"sig":500,"net":"iscgem","code":"872922","ids":",iscgem872922,","sources":",iscgem,","types":",origin,shakemap,","nst":null,"dmin":null,"rms":null,"gap":null,"magType":"mw","type":"earthquake","title":"M 5.7 - New Britain region, Papua New Guinea"},"geometry":{"type":"Point","coordinates":[152.284,-4.871,45]},"id":"iscgem872922"},
{"type":"Feature","properties":{"mag":5.8,"place":"Tonga","time":-201492442000,"updated":1431543177000,"tz":null,"url":"https://earthquake.usgs.gov/earthquakes/eventpage/iscgem872920","detail":"https://earthquake.usgs.gov/fdsnws/event/1/query?eventid=iscgem872920&format=geojson","felt":null,"cdi":null,"mmi":null,"alert":null,"status":"automatic","tsunami":0,"sig":518,"net":"iscgem","code":"872920","ids":",iscgem872920,","sources":",iscgem,","types":",origin,","nst":null,"dmin":null,"rms":null,"gap":null,"magType":"mw","type":"earthquake","title":"M 5.8 - Tonga"},"geometry":{"type":"Point","coordinates":[-173.744,-19.534,25]},"id":"iscgem872920"},
{"type":"Feature","properties":{"mag":4.09,"place":"67km ENE of Beatty, NV","time":-201572098810,"updated":1454010526420,"tz":null,"url":"https://earthquake.usgs.gov/earthquakes/eventpage/ci3332183","detail":"https://earthquake.usgs.gov/fdsnws/event/1/query?eventid=ci3332183&format=geojson","felt":null,"cdi":null,"mmi":null,"alert":null,"status":"reviewed","tsunami":0,"sig":257,"net":"ci","code":"3332183","ids":",ci3332183,","sources":",ci,","types":",origin,phase-data,","nst":12,"dmin":1.768,"rms":0.61,"gap":262,"magType":"ml","type":"nuclear explosion","title":"M 4.1 Nuclear Explosion - 67km ENE of Beatty, NV"},"geometry":{"type":"Point","coordinates":[-116.0156667,37.0416667,0.3]},"id":"ci3332183"},
{"type":"Feature","properties":{"mag":2.46,"place":"Hawaii region, Hawaii","time":-201581419190,"updated":1585675018470,"tz":null,"url":"https://earthquake.usgs.gov/earthquakes/eventpage/hv19630750","detail":"https://earthquake.usgs.gov/fdsnws/event/1/query?eventid=hv19630750&format=geojson","felt":null,"cdi":null,"mmi":null,"alert":null,"status":"reviewed","tsunami":0,"sig":93,"net":"hv","code":"19630750","ids":",hv19630750,","sources":",hv,","types":",origin,phase-data,","nst":8,"dmin":null,"rms":0.08,"gap":228,"magType":"ml","type":"earthquake","title":"M 2.5 - Hawaii region, Hawaii"},"geometry":{"type":"Point","coordinates":[-155.2336667,19.3021667,-0.352]},"id":"hv19630750"},
{"type":"Feature","properties":{"mag":2.43,"place":"Hawaii region, Hawaii","time":-201779391560,"updated":1585675018320,"tz":null,"url":"https://earthquake.usgs.gov/earthquakes/eventpage/hv19630749","detail":"https://earthquake.usgs.gov/fdsnws/event/1/query?eventid=hv19630749&format=geojson","felt":null,"cdi":null,"mmi":null,"alert":null,"status":"reviewed","tsunami":0,"sig":91,"net":"hv","code":"19630749","ids":",hv19630749,","sources":",hv,","types":",origin,phase-data,","nst":9,"dmin":null,"rms":0.12,"gap":99,"magType":"ml","type":"earthquake","title":"M 2.4 - Hawaii region, Hawaii"},"geometry":{"type":"Point","coordinates":[-155.2471667,19.4456667,19.843]},"id":"hv19630749"},
{"type":"Feature","properties":{"mag":2.62,"place":"19km WSW of Volcano, Hawaii","time":-201813496620,"updated":1585675018160,"tz":-600,"url":"https://earthquake.usgs.gov/earthquakes/eventpage/hv19630748","detail":"https://earthquake.usgs.gov/fdsnws/event/1/query?eventid=hv19630748&format=geojson","felt":null,"cdi":null,"mmi":null,"alert":null,"status":"reviewed","tsunami":0,"sig":106,"net":"hv","code":"19630748","ids":",hv19630748,","sources":",hv,","types":",geoserve,origin,phase-data,","nst":8,"dmin":null,"rms":0.17,"gap":222,"magType":"ml","type":"earthquake","title":"M 2.6 - 19km WSW of Volcano, Hawaii"},"geometry":{"type":"Point","coordinates":[-155.411,19.375,11.758]},"id":"hv19630748"},
{"type":"Feature","properties":{"mag":6,"place":"Tonga","time":-201864193000,"updated":1431543177000,"tz":null,"url":"https://earthquake.usgs.gov/earthquakes/eventpage/iscgem872900","detail":"https://earthquake.usgs.gov/fdsnws/event/1/query?eventid=iscgem872900&format=geojson","felt":null,"cdi":null,"mmi":null,"alert":null,"status":"automatic","tsunami":0,"sig":554,"net":"iscgem","code":"872900","ids":",iscgem872900,","sources":",iscgem,","types":",origin,","nst":null,"dmin":null,"rms":null,"gap":null,"magType":"mw","type":"earthquake","title":"M 6.0 - Tonga"},"geometry":{"type":"Point","coordinates":[-175.739,-15.299,25]},"id":"iscgem872900"},
{"type":"Feature","properties":{"mag":1.61,"place":"19km ENE of Pahala, Hawaii","time":-201872987470,"updated":1585675018030,"tz":-600,"url":"https://earthquake.usgs.gov/earthquakes/eventpage/hv19630747","detail":"https://earthquake.usgs.gov/fdsnws/event/1/query?eventid=hv19630747&format=geojson","felt":null,"cdi":null,"mmi":null,"alert":null,"status":"reviewed","tsunami":0,"sig":40,"net":"hv","code":"19630747","ids":",hv19630747,","sources":",hv,","types":",geoserve,origin,phase-data,","nst":7,"dmin":null,"rms":0.06,"gap":268,"magType":"ml","type":"earthquake","title":"M 1.6 - 19km ENE of Pahala, Hawaii"},"geometry":{"type":"Point","coordinates":[-155.304,19.2491667,31.766]},"id":"hv19630747"},
{"type":"Feature","properties":{"mag":2.61,"place":"3km SSW of Paramount, CA","time":-201887200960,"updated":1454009996130,"tz":null,"url":"https://earthquake.usgs.gov/earthquakes/eventpage/ci3331251","detail":"https://earthquake.usgs.gov/fdsnws/event/1/query?eventid=ci3331251&format=geojson","felt":null,"cdi":null,"mmi":null,"alert":null,"status":"reviewed","tsunami":0,"sig":105,"net":"ci","code":"3331251","ids":",ci3331251,","sources":",ci,","types":",origin,phase-data,","nst":9,"dmin":0.2834,"rms":0.61,"gap":110,"magType":"ml","type":"earthquake","title":"M 2.6 - 3km SSW of Paramount, CA"},"geometry":{"type":"Point","coordinates":[-118.1685,33.8643333,0.03]},"id":"ci3331251"},
{"type":"Feature","properties":{"mag":2.58,"place":"Hawaii region, Hawaii","time":-201887747100,"updated":1585675017890,"tz":null,"url":"https://earthquake.usgs.gov/earthquakes/eventpage/hv19630746","detail":"https://earthquake.usgs.gov/fdsnws/event/1/query?eventid=hv19630746&format=geojson","felt":null,"cdi":null,"mmi":null,"alert":null,"status":"reviewed","tsunami":0,"sig":102,"net":"hv","code":"19630746","ids":",hv19630746,","sources":",hv,","types":",origin,phase-data,","nst":9,"dmin":null,"rms":0.14,"gap":235,"magType":"ml","type":"earthquake","title":"M 2.6 - Hawaii region, Hawaii"},"geometry":{"type":"Point","coordinates":[-155.2233333,19.2875,7.173]},"id":"hv19630746"},
{"type":"Feature","properties":{"mag":3.37,"place":"6km SSW of Volcano, Hawaii","time":-201908739960,"updated":1585675017750,"tz":-600,"url":"https://earthquake.usgs.gov/earthquakes/eventpage/hv19630745","detail":"https://earthquake.usgs.gov/fdsnws/event/1/query?eventid=hv19630745&format=geojson","felt":null,"cdi":null,"mmi":null,"alert":null,"status":"reviewed","tsunami":0,"sig":175,"net":"hv","code":"19630745","ids":",hv19630745,","sources":",hv,","types":",geoserve,origin,phase-data,","nst":9,"dmin":null,"rms":0.09,"gap":137,"magType":"ml","type":"earthquake","title":"M 3.4 - 6km SSW of Volcano, Hawaii"},"geometry":{"type":"Point","coordinates":[-155.2598333,19.374,29.803]},"id":"hv19630745"},
{"type":"Feature","properties":{"mag":2.58,"place":"Hawaii region, Hawaii","time":-201908764450,"updated":1585675017610,"tz":null,"url":"https://earthquake.usgs.gov/earthquakes/eventpage/hv19630744","detail":"https://earthquake.usgs.gov/fdsnws/event/1/query?eventid=hv19630744&format=geojson","felt":null,"cdi":null,"mmi":null,"alert":null,"status":"reviewed","tsunami":0,"sig":102,"net":"hv","code":"19630744","ids":",hv19630744,","sources":",hv,","types":",origin,phase-data,","nst":9,"dmin":null,"rms":0.06,"gap":189,"magType":"ml","type":"earthquake","title":"M 2.6 - Hawaii region, Hawaii"},"geometry":{"type":"Point","coordinates":[-155.247,19.3433333,29.273]},"id":"hv19630744"},
{"type":"Feature","properties":{"mag":6,"place":"New Britain region, Papua New Guinea","time":-201962627000,"updated":1594351229231,"tz":null,"url":"https://earthquake.usgs.gov/earthquakes/eventpage/iscgem872896","detail":"https://earthquake.usgs.gov/fdsnws/event/1/query?eventid=iscgem872896&format=geojson","felt":null,"cdi":null,"mmi":4.712,"alert":null,"status":"automatic","tsunami":0,"sig":554,"net":"iscgem","code":"872896","ids":",iscgem872896,","sources":",iscgem,","types":",origin,shakemap,","nst":null,"dmin":null,"rms":null,"gap":null,"magType":"mw","type":"earthquake","title":"M 6.0 - New Britain region, Papua New Guinea"},"geometry":{"type":"Point","coordinates":[151.074,-5.743,50]},"id":"iscgem872896"},
{"type":"Feature","properties":{"mag":5.8,"place":"Komandorskiye Ostrova, Russia region","time":-201995101000,"updated":1431543177000,"tz":null,"url":"https://earthquake.usgs.gov/earthquakes/eventpage/iscgem872895","detail":"https://earthquake.usgs.gov/fdsnws/event/1/query?eventid=iscgem872895&format=geojson","felt":null,"cdi":null,"mmi":null,"alert":null,"status":"automatic","tsunami":0,"sig":518,"net":"iscgem","code":"872895","ids":",iscgem872895,","sources":",iscgem,","types":",origin,","nst":null,"dmin":null,"rms":null,"gap":null,"magType":"mw","type":"earthquake","title":"M 5.8 - Komandorskiye Ostrova, Russia region"},"geometry":{"type":"Point","coordinates":[168.164,54.239,50]},"id":"iscgem872895"},
{"type":"Feature","properties":{"mag":2.99,"place":"3km ENE of Kailua-Kona, Hawaii","time":-202025135670,"updated":1585675017470,"tz":-600,"url":"https://earthquake.usgs.gov/earthquakes/eventpage/hv19630743","detail":"https://earthquake.usgs.gov/fdsnws/event/1/query?eventid=hv19630743&format=geojson","felt":null,"cdi":null,"mmi":null,"alert":null,"status":"reviewed","tsunami":0,"sig":138,"net":"hv","code":"19630743","ids":",hv19630743,","sources":",hv,","types":",geoserve,origin,phase-data,","nst":8,"dmin":null,"rms":0.3,"gap":318,"magType":"ml","type":"earthquake","title":"M 3.0 - 3km ENE of Kailua-Kona, Hawaii"},"geometry":{"type":"Point","coordinates":[-155.9638333,19.6605,5.678]},"id":"hv19630743"},
{"type":"Feature","properties":{"mag":3.57,"place":"6km ENE of San Jacinto, CA","time":-202090873820,"updated":1454011292310,"tz":null,"url":"https://earthquake.usgs.gov/earthquakes/eventpage/ci3331250","detail":"https://earthquake.usgs.gov/fdsnws/event/1/query?eventid=ci3331250&format=geojson","felt":null,"cdi":null,"mmi":null,"alert":null,"status":"reviewed","tsunami":0,"sig":196,"net":"ci","code":"3331250","ids":",ci3331250,","sources":",ci,","types":",origin,phase-data,","nst":11,"dmin":0.4312,"rms":0.59,"gap":114,"magType":"ml","type":"earthquake","title":"M 3.6 - 6km ENE of San Jacinto, CA"},"geometry":{"type":"Point","coordinates":[-116.9065,33.8091667,6]},"id":"ci3331250"},
{"type":"Feature","properties":{"mag":2.86,"place":"7km ENE of North Tustin, CA","time":-202109023600,"updated":1454010266180,"tz":null,"url":"https://earthquake.usgs.gov/earthquakes/eventpage/ci3331249","detail":"https://earthquake.usgs.gov/fdsnws/event/1/query?eventid=ci3331249&format=geojson","felt":null,"cdi":null,"mmi":null,"alert":null,"status":"reviewed","tsunami":0,"sig":126,"net":"ci","code":"3331249","ids":",ci3331249,","sources":",ci,","types":",origin,phase-data,","nst":8,"dmin":0.351,"rms":0.61,"gap":173,"magType":"ml","type":"earthquake","title":"M 2.9 - 7km ENE of North Tustin, CA"},"geometry":{"type":"Point","coordinates":[-117.728,33.8001667,3.95]},"id":"ci3331249"},
{"type":"Feature","properties":{"mag":3.14,"place":"25km NNW of Tehachapi, CA","time":-202115660420,"updated":1454009995640,"tz":null,"url":"https://earthquake.usgs.gov/earthquakes/eventpage/ci3331248","detail":"https://earthquake.usgs.gov/fdsnws/event/1/query?eventid=ci3331248&format=geojson","felt":null,"cdi":null,"mmi":null,"alert":null,"status":"reviewed","tsunami":0,"sig":152,"net":"ci","code":"3331248","ids":",ci3331248,","sources":",ci,","types":",origin,phase-data,","nst":11,"dmin":0.3262,"rms":0.5,"gap":100,"magType":"ml","type":"earthquake","title":"M 3.1 - 25km NNW of Tehachapi, CA"},"geometry":{"type":"Point","coordinates":[-118.555,35.3426667,6]},"id":"ci3331248"},
{"type":"Feature","properties":{"mag":5.5,"place":"Reykjanes Ridge","time":-202127004000,"updated":1431543177000,"tz":null,"url":"https://earthquake.usgs.gov/earthquakes/eventpage/iscgem872892","detail":"https://earthquake.usgs.gov/fdsnws/event/1/query?eventid=iscgem872892&format=geojson","felt":null,"cdi":null,"mmi":null,"alert":null,"status":"automatic","tsunami":0,"sig":465,"net":"iscgem","code":"872892","ids":",iscgem872892,","sources":",iscgem,","types":",origin,","nst":null,"dmin":null,"rms":null,"gap":null,"magType":"mw","type":"earthquake","title":"M 5.5 - Reykjanes Ridge"},"geometry":{"type":"Point","coordinates":[-33.855,57.048,20]},"id":"iscgem872892"},
{"type":"Feature","properties":{"mag":2.24,"place":"5km S of Volcano, Hawaii","time":-202158056870,"updated":1585675017330,"tz":-600,"url":"https://earthquake.usgs.gov/earthquakes/eventpage/hv19630742","detail":"https://earthquake.usgs.gov/fdsnws/event/1/query?eventid=hv19630742&format=geojson","felt":null,"cdi":null,"mmi":null,"alert":null,"status":"reviewed","tsunami":0,"sig":77,"net":"hv","code":"19630742","ids":",hv19630742,","sources":",hv,","types":",geoserve,origin,phase-data,","nst":6,"dmin":null,"rms":0.01,"gap":152,"magType":"ml","type":"earthquake","title":"M 2.2 - 5km S of Volcano, Hawaii"},"geometry":{"type":"Point","coordinates":[-155.2416667,19.379,26.971]},"id":"hv19630742"},
{"type":"Feature","properties":{"mag":2.55,"place":"Hawaii region, Hawaii","time":-202186049160,"updated":1585675017190,"tz":null,"url":"https://earthquake.usgs.gov/earthquakes/eventpage/hv19630741","detail":"https://earthquake.usgs.gov/fdsnws/event/1/query?eventid=hv19630741&format=geojson","felt":null,"cdi":null,"mmi":null,"alert":null,"status":"reviewed","tsunami":0,"sig":100,"net":"hv","code":"19630741","ids":",hv19630741,","sources":",hv,","types":",origin,phase-data,","nst":7,"dmin":null,"rms":0.06,"gap":267,"magType":"ml","type":"earthquake","title":"M 2.6 - Hawaii region, Hawaii"},"geometry":{"type":"Point","coordinates":[-155.3053333,20.0281667,6.368]},"id":"hv19630741"},
{"type":"Feature","properties":{"mag":3.02,"place":"Hawaii region, Hawaii","time":-202196679550,"updated":1585675017050,"tz":null,"url":"https://earthquake.usgs.gov/earthquakes/eventpage/hv19630740","detail":"https://earthquake.usgs.gov/fdsnws/event/1/query?eventid=hv19630740&format=geojson","felt":null,"cdi":null,"mmi":null,"alert":null,"status":"reviewed","tsunami":0,"sig":140,"net":"hv","code":"19630740","ids":",hv19630740,","sources":",hv,","types":",origin,phase-data,","nst":10,"dmin":null,"rms":0.22,"gap":244,"magType":"ml","type":"earthquake","title":"M 3.0 - Hawaii region, Hawaii"},"geometry":{"type":"Point","coordinates":[-155.2188333,19.2666667,5.853]},"id":"hv19630740"},
{"type":"Feature","properties":{"mag":5.8,"place":"west of Macquarie Island","time":-202206053000,"updated":1431543177000,"tz":null,"url":"https://earthquake.usgs.gov/earthquakes/eventpage/iscgem872889","detail":"https://earthquake.usgs.gov/fdsnws/event/1/query?eventid=iscgem872889&format=geojson","felt":null,"cdi":null,"mmi":null,"alert":null,"status":"automatic","tsunami":0,"sig":518,"net":"iscgem","code":"872889","ids":",iscgem872889,","sources":",iscgem,","types":",origin,","nst":null,"dmin":null,"rms":null,"gap":null,"magType":"mw","type":"earthquake","title":"M 5.8 - west of Macquarie Island"},"geometry":{"type":"Point","coordinates":[153.973,-60.694,15]},"id":"iscgem872889"},
{"type":"Feature","properties":{"mag":3.35,"place":"Hawaii region, Hawaii","time":-202280787930,"updated":1585675016890,"tz":null,"url":"https://earthquake.usgs.gov/earthquakes/eventpage/hv19630739","detail":"https://earthquake.usgs.gov/fdsnws/event/1/query?eventid=hv19630739&format=geojson","felt":null,"cdi":null,"mmi":null,"alert":null,"status":"reviewed","tsunami":0,"sig":173,"net":"hv","code":"19630739","ids":",hv19630739,","sources":",hv,","types":",origin,phase-data,","nst":10,"dmin":null,"rms":0.12,"gap":228,"magType":"ml","type":"earthquake","title":"M 3.4 - Hawaii region, Hawaii"},"geometry":{"type":"Point","coordinates":[-155.1586667,20.1453333,2.96]},"id":"hv19630739"},
{"type":"Feature","properties":{"mag":2.22,"place":"3km SSE of Volcano, Hawaii","time":-202284301700,"updated":1585675016740,"tz":-600,"url":"https://earthquake.usgs.gov/earthquakes/eventpage/hv19630738","detail":"https://earthquake.usgs.gov/fdsnws/event/1/query?eventid=hv19630738&format=geojson","felt":null,"cdi":null,"mmi":null,"alert":null,"status":"reviewed","tsunami":0,"sig":76,"net":"hv","code":"19630738","ids":",hv19630738,","sources":",hv,","types":",geoserve,origin,phase-data,","nst":10,"dmin":null,"rms":0.14,"gap":107,"magType":"ml","type":"earthquake","title":"M 2.2 - 3km SSE of Volcano, Hawaii"},"geometry":{"type":"Point","coordinates":[-155.2235,19.4063333,28.993]},"id":"hv19630738"},
{"type":"Feature","properties":{"mag":2.24,"place":"10km S of Volcano, Hawaii","time":-202286540360,"updated":1585675016600,"tz":-600,"url":"https://earthquake.usgs.gov/earthquakes/eventpage/hv19630737","detail":"https://earthquake.usgs.gov/fdsnws/event/1/query?eventid=hv19630737&format=geojson","felt":null,"cdi":null,"mmi":null,"alert":null,"status":"reviewed","tsunami":0,"sig":77,"net":"hv","code":"19630737","ids":",hv19630737,","sources":",hv,","types":",geoserve,origin,phase-data,","nst":8,"dmin":null,"rms":0.21,"gap":205,"magType":"ml","type":"earthquake","title":"M 2.2 - 10km S of Volcano, Hawaii"},"geometry":{"type":"Point","coordinates":[-155.2191667,19.3358333,-0.838]},"id":"hv19630737"},
{"type":"Feature","properties":{"mag":2.26,"place":"17km SE of Volcano, Hawaii","time":-202299245180,"updated":1585675016460,"tz":-600,"url":"https://earthquake.usgs.gov/earthquakes/eventpage/hv19630736","detail":"https://earthquake.usgs.gov/fdsnws/event/1/query?eventid=hv19630736&format=geojson","felt":null,"cdi":null,"mmi":null,"alert":null,"status":"reviewed","tsunami":0,"sig":79,"net":"hv","code":"19630736","ids":",hv19630736,","sources":",hv,","types":",geoserve,origin,phase-data,","nst":9,"dmin":null,"rms":0.08,"gap":227,"magType":"ml","type":"earthquake","title":"M 2.3 - 17km SE of Volcano, Hawaii"},"geometry":{"type":"Point","coordinates":[-155.0991667,19.3375,8.703]},"id":"hv19630736"},
{"type":"Feature","properties":{"mag":2.46,"place":"10km SE of Volcano, Hawaii","time":-202302174330,"updated":1585675016310,"tz":-600,"url":"https://earthquake.usgs.gov/earthquakes/eventpage/hv19630735","detail":"https://earthquake.usgs.gov/fdsnws/event/1/query?eventid=hv19630735&format=geojson","felt":null,"cdi":null,"mmi":null,"alert":null,"status":"reviewed","tsunami":0,"sig":93,"net":"hv","code":"19630735","ids":",hv19630735,","sources":",hv,","types":",geoserve,origin,phase-data,","nst":7,"dmin":null,"rms":0.24,"gap":130,"magType":"ml","type":"earthquake","title":"M 2.5 - 10km SE of Volcano, Hawaii"},"geometry":{"type":"Point","coordinates":[-155.1666667,19.3638333,10.593]},"id":"hv19630735"},
{"type":"Feature","properties":{"mag":2.41,"place":"9km S of Volcano, Hawaii","time":-202306806110,"updated":1585675016170,"tz":-600,"url":"https://earthquake.usgs.gov/earthquakes/eventpage/hv19630734","detail":"https://earthquake.usgs.gov/fdsnws/event/1/query?eventid=hv19630734&format=geojson","felt":null,"cdi":null,"mmi":null,"alert":null,"status":"reviewed","tsunami":0,"sig":89,"net":"hv","code":"19630734","ids":",hv19630734,","sources":",hv,","types":",geoserve,origin,phase-data,","nst":7,"dmin":null,"rms":0.16,"gap":247,"magType":"ml","type":"earthquake","title":"M 2.4 - 9km S of Volcano, Hawaii"},"geometry":{"type":"Point","coordinates":[-155.2211667,19.3453333,-0.896]},"id":"hv19630734"},
{"type":"Feature","properties":{"mag":2.34,"place":"Hawaii region, Hawaii","time":-202308371770,"updated":1585675016030,"tz":null,"url":"https://earthquake.usgs.gov/earthquakes/eventpage/hv19630733","detail":"https://earthquake.usgs.gov/fdsnws/event/1/query?eventid=hv19630733&format=geojson","felt":null,"cdi":null,"mmi":null,"alert":null,"status":"reviewed","tsunami":0,"sig":84,"net":"hv","code":"19630733","ids":",hv19630733,","sources":",hv,","types":",origin,phase-data,","nst":11,"dmin":null,"rms":0.13,"gap":83,"magType":"ml","type":"earthquake","title":"M 2.3 - Hawaii region, Hawaii"},"geometry":{"type":"Point","coordinates":[-155.2436667,19.411,26.033]},"id":"hv19630733"},
{"type":"Feature","properties":{"mag":2.55,"place":"Hawaii region, Hawaii","time":-202309548410,"updated":1585675015860,"tz":null,"url":"https://earthquake.usgs.gov/earthquakes/eventpage/hv19630732","detail":"https://earthquake.usgs.gov/fdsnws/event/1/query?eventid=hv19630732&format=geojson","felt":null,"cdi":null,"mmi":null,"alert":null,"status":"reviewed","tsunami":0,"sig":100,"net":"hv","code":"19630732","ids":",hv19630732,","sources":",hv,","types":",origin,phase-data,","nst":7,"dmin":null,"rms":0.07,"gap":241,"magType":"ml","type":"earthquake","title":"M 2.6 - Hawaii region, Hawaii"},"geometry":{"type":"Point","coordinates":[-155.2376667,19.3531667,2.011]},"id":"hv19630732"},
{"type":"Feature","properties":{"mag":2.73,"place":"Hawaii region, Hawaii","time":-202312151230,"updated":1585675015700,"tz":null,"url":"https://earthquake.usgs.gov/earthquakes/eventpage/hv19630731","detail":"https://earthquake.usgs.gov/fdsnws/event/1/query?eventid=hv19630731&format=geojson","felt":null,"cdi":null,"mmi":null,"alert":null,"status":"reviewed","tsunami":0,"sig":115,"net":"hv","code":"19630731","ids":",hv19630731,","sources":",hv,","types":",origin,phase-data,","nst":7,"dmin":null,"rms":0.13,"gap":177,"magType":"ml","type":"earthquake","title":"M 2.7 - Hawaii region, Hawaii"},"geometry":{"type":"Point","coordinates":[-155.2201667,19.3561667,-0.559]},"id":"hv19630731"},
{"type":"Feature","properties":{"mag":2.27,"place":"Hawaii region, Hawaii","time":-202313546180,"updated":1585675015550,"tz":null,"url":"https://earthquake.usgs.gov/earthquakes/eventpage/hv19630730","detail":"https://earthquake.usgs.gov/fdsnws/event/1/query?eventid=hv19630730&format=geojson","felt":null,"cdi":null,"mmi":null,"alert":null,"status":"reviewed","tsunami":0,"sig":79,"net":"hv","code":"19630730","ids":",hv19630730,","sources":",hv,","types":",origin,phase-data,","nst":7,"dmin":null,"rms":0.37,"gap":242,"magType":"ml","type":"earthquake","title":"M 2.3 - Hawaii region, Hawaii"},"geometry":{"type":"Point","coordinates":[-155.2018333,19.311,-0.451]},"id":"hv19630730"},
{"type":"Feature","properties":{"mag":2.39,"place":"Hawaii region, Hawaii","time":-202315137330,"updated":1585675015420,"tz":null,"url":"https://earthquake.usgs.gov/earthquakes/eventpage/hv19630729","detail":"https://earthquake.usgs.gov/fdsnws/event/1/query?eventid=hv19630729&format=geojson","felt":null,"cdi":null,"mmi":null,"alert":null,"status":"reviewed","tsunami":0,"sig":88,"net":"hv","code":"19630729","ids":",hv19630729,","sources":",hv,","types":",origin,phase-data,","nst":8,"dmin":null,"rms":0.13,"gap":179,"magType":"ml","type":"earthquake","title":"M 2.4 - Hawaii region, Hawaii"},"geometry":{"type":"Point","coordinates":[-155.2173333,19.3558333,-0.949]},"id":"hv19630729"},
{"type":"Feature","properties":{"mag":5.5,"place":"south of Bali, Indonesia","time":-202323077000,"updated":1431543177000,"tz":null,"url":"https://earthquake.usgs.gov/earthquakes/eventpage/iscgem872878","detail":"https://earthquake.usgs.gov/fdsnws/event/1/query?eventid=iscgem872878&format=geojson","felt":null,"cdi":null,"mmi":null,"alert":null,"status":"automatic","tsunami":0,"sig":465,"net":"iscgem","code":"872878","ids":",iscgem872878,","sources":",iscgem,","types":",origin,","nst":null,"dmin":null,"rms":null,"gap":null,"magType":"mw","type":"earthquake","title":"M 5.5 - south of Bali, Indonesia"},"geometry":{"type":"Point","coordinates":[114.329,-9.148,65]},"id":"iscgem872878"},
{"type":"Feature","properties":{"mag":2.72,"place":"28km ENE of Honaunau-Napoopoo, Hawaii","time":-202347937640,"updated":1585675034810,"tz":-600,"url":"https://earthquake.usgs.gov/earthquakes/eventpage/hv19630728","detail":"https://earthquake.usgs.gov/fdsnws/event/1/query?eventid=hv19630728&format=geojson","felt":null,"cdi":null,"mmi":null,"alert":null,"status":"reviewed","tsunami":0,"sig":114,"net":"hv","code":"19630728","ids":",hv19630728,","sources":",hv,","types":",geoserve,origin,phase-data,","nst":6,"dmin":null,"rms":0.03,"gap":323,"magType":"ml","type":"earthquake","title":"M 2.7 - 28km ENE of Honaunau-Napoopoo, Hawaii"},"geometry":{"type":"Point","coordinates":[-155.6033333,19.5073333,16.608]},"id":"hv19630728"},
{"type":"Feature","properties":{"mag":2.72,"place":"Hawaii region, Hawaii","time":-202375116710,"updated":1585675015280,"tz":null,"url":"https://earthquake.usgs.gov/earthquakes/eventpage/hv19630727","detail":"https://earthquake.usgs.gov/fdsnws/event/1/query?eventid=hv19630727&format=geojson","felt":null,"cdi":null,"mmi":null,"alert":null,"status":"reviewed","tsunami":0,"sig":114,"net":"hv","code":"19630727","ids":",hv19630727,","sources":",hv,","types":",origin,phase-data,","nst":9,"dmin":null,"rms":0.11,"gap":332,"magType":"ml","type":"earthquake","title":"M 2.7 - Hawaii region, Hawaii"},"geometry":{"type":"Point","coordinates":[-155.0001667,18.7636667,8.086]},"id":"hv19630727"},
{"type":"Feature","properties":{"mag":3.15,"place":"8km W of Twentynine Palms, CA","time":-202380250260,"updated":1454009995110,"tz":null,"url":"https://earthquake.usgs.gov/earthquakes/eventpage/ci3331247","detail":"https://earthquake.usgs.gov/fdsnws/event/1/query?eventid=ci3331247&format=geojson","felt":null,"cdi":null,"mmi":null,"alert":null,"status":"reviewed","tsunami":0,"sig":153,"net":"ci","code":"3331247","ids":",ci3331247,","sources":",ci,","types":",origin,phase-data,","nst":6,"dmin":0.6072,"rms":0.5,"gap":158,"magType":"ml","type":"earthquake","title":"M 3.2 - 8km W of Twentynine Palms, CA"},"geometry":{"type":"Point","coordinates":[-116.1605,34.1333333,6]},"id":"ci3331247"},
{"type":"Feature","properties":{"mag":6.9,"place":"central Mid-Atlantic Ridge","time":-202397906000,"updated":1431543177000,"tz":null,"url":"https://earthquake.usgs.gov/earthquakes/eventpage/iscgem872872","detail":"https://earthquake.usgs.gov/fdsnws/event/1/query?eventid=iscgem872872&format=geojson","felt":null,"cdi":null,"mmi":null,"alert":null,"status":"automatic","tsunami":0,"sig":732,"net":"iscgem","code":"872872","ids":",iscgem872872,","sources":",iscgem,","types":",origin,","nst":null,"dmin":null,"rms":null,"gap":null,"magType":"mw","type":"earthquake","title":"M 6.9 - central Mid-Atlantic Ridge"},"geometry":{"type":"Point","coordinates":[-35.877,7.367,15]},"id":"iscgem872872"},
{"type":"Feature","properties":{"mag":2.22,"place":"16km SW of Leilani Estates, Hawaii","time":-202421103300,"updated":1585675015130,"tz":-600,"url":"https://earthquake.usgs.gov/earthquakes/eventpage/hv19630726","detail":"https://earthquake.usgs.gov/fdsnws/event/1/query?eventid=hv19630726&format=geojson","felt":null,"cdi":null,"mmi":null,"alert":null,"status":"reviewed","tsunami":0,"sig":76,"net":"hv","code":"19630726","ids":",hv19630726,","sources":",hv,","types":",geoserve,origin,phase-data,","nst":8,"dmin":null,"rms":0.12,"gap":246,"magType":"ml","type":"earthquake","title":"M 2.2 - 16km SW of Leilani Estates, Hawaii"},"geometry":{"type":"Point","coordinates":[-155.0075,19.3488333,8.673]},"id":"hv19630726"},
{"type":"Feature","properties":{"mag":3.17,"place":"5km S of Volcano, Hawaii","time":-202432016530,"updated":1585675014980,"tz":-600,"url":"https://earthquake.usgs.gov/earthquakes/eventpage/hv19630725","detail":"https://earthquake.usgs.gov/fdsnws/event/1/query?eventid=hv19630725&format=geojson","felt":null,"cdi":null,"mmi":null,"alert":null,"status":"reviewed","tsunami":0,"sig":155,"net":"hv","code":"19630725","ids":",hv19630725,","sources":",hv,","types":",geoserve,origin,phase-data,","nst":11,"dmin":null,"rms":0.18,"gap":160,"magType":"ml","type":"earthquake","title":"M 3.2 - 5km S of Volcano, Hawaii"},"geometry":{"type":"Point","coordinates":[-155.2336667,19.378,29.027]},"id":"hv19630725"},
{"type":"Feature","properties":{"mag":2.59,"place":"Hawaii region, Hawaii","time":-202449210990,"updated":1585675014840,"tz":null,"url":"https://earthquake.usgs.gov/earthquakes/eventpage/hv19630724","detail":"https://earthquake.usgs.gov/fdsnws/event/1/query?eventid=hv19630724&format=geojson","felt":null,"cdi":null,"mmi":null,"alert":null,"status":"reviewed","tsunami":0,"sig":103,"net":"hv","code":"19630724","ids":",hv19630724,","sources":",hv,","types":",origin,phase-data,","nst":6,"dmin":null,"rms":0.06,"gap":153,"magType":"ml","type":"earthquake","title":"M 2.6 - Hawaii region, Hawaii"},"geometry":{"type":"Point","coordinates":[-155.2525,19.3865,30.003]},"id":"hv19630724"},
{"type":"Feature","properties":{"mag":2.77,"place":"Hawaii region, Hawaii","time":-202458959910,"updated":1585675014700,"tz":null,"url":"https://earthquake.usgs.gov/earthquakes/eventpage/hv19630723","detail":"https://earthquake.usgs.gov/fdsnws/event/1/query?eventid=hv19630723&format=geojson","felt":null,"cdi":null,"mmi":null,"alert":null,"status":"reviewed","tsunami":0,"sig":118,"net":"hv","code":"19630723","ids":",hv19630723,","sources":",hv,","types":",origin,phase-data,","nst":6,"dmin":null,"rms":0.09,"gap":340,"magType":"ml","type":"earthquake","title":"M 2.8 - Hawaii region, Hawaii"},"geometry":{"type":"Point","coordinates":[-155.8458333,19.5231667,4.998]},"id":"hv19630723"},
{"type":"Feature","properties":{"mag":2.98,"place":"6km NW of Twentynine Palms, CA","time":-202554159120,"updated":1454010265700,"tz":null,"url":"https://earthquake.usgs.gov/earthquakes/eventpage/ci3331246","detail":"https://earthquake.usgs.gov/fdsnws/event/1/query?eventid=ci3331246&format=geojson","felt":null,"cdi":null,"mmi":null,"alert":null,"status":"reviewed","tsunami":0,"sig":137,"net":"ci","code":"3331246","ids":",ci3331246,","sources":",ci,","types":",origin,phase-data,","nst":7,"dmin":0.614,"rms":0.58,"gap":164,"magType":"ml","type":"earthquake","title":"M 3.0 - 6km NW of Twentynine Palms, CA"},"geometry":{"type":"Point","coordinates":[-116.1268333,34.1695,6]},"id":"ci3331246"},
{"type":"Feature","properties":{"mag":3.07,"place":"4km SSW of Volcano, Hawaii","time":-202567747510,"updated":1585675014550,"tz":-600,"url":"https://earthquake.usgs.gov/earthquakes/eventpage/hv19630722","detail":"https://earthquake.usgs.gov/fdsnws/event/1/query?eventid=hv19630722&format=geojson","felt":null,"cdi":null,"mmi":null,"alert":null,"status":"reviewed","tsunami":0,"sig":145,"net":"hv","code":"19630722","ids":",hv19630722,","sources":",hv,","types":",geoserve,origin,phase-data,","nst":10,"dmin":null,"rms":0.11,"gap":102,"magType":"ml","type":"earthquake","title":"M 3.1 - 4km SSW of Volcano, Hawaii"},"geometry":{"type":"Point","coordinates":[-155.2535,19.3883333,30.493]},"id":"hv19630722"}],"bbox":[-178.684,-60.694,-1.252,168.164,57.048,570]}